{
  "schema_version": "2.0.0",
  "generated_at": "2026-07-15T22:53:36+09:00",
  "run_id": "1784123625",
  "status": "ok",
  "source": "Yahoo Finance + 네이버 금융",
  "indices": [
    {
      "name": "S&P 500",
      "symbol": "^GSPC",
      "group": "주가지수",
      "unit": "",
      "price": 7560.33,
      "prev_close": 7515.34,
      "change": 44.98999999999978,
      "change_pct": 0.5986422437308196,
      "currency": "USD",
      "market_time": 1784123616
    },
    {
      "name": "나스닥",
      "symbol": "^IXIC",
      "group": "주가지수",
      "unit": "",
      "price": 26188.441,
      "prev_close": 25873.18,
      "change": 315.2609999999986,
      "change_pct": 1.2184857060477243,
      "currency": "USD",
      "market_time": 1784123616
    },
    {
      "name": "다우존스",
      "symbol": "^DJI",
      "group": "주가지수",
      "unit": "",
      "price": 52649.56,
      "prev_close": 52498.64,
      "change": 150.91999999999825,
      "change_pct": 0.28747411361513037,
      "currency": "USD",
      "market_time": 1784123619
    },
    {
      "name": "미 3개월물(T-Bill)",
      "symbol": "^IRX",
      "group": "미국채 금리",
      "unit": "%",
      "price": 3.69,
      "prev_close": 3.7,
      "change": -0.010000000000000231,
      "change_pct": -0.2702702702702765,
      "currency": "USD",
      "market_time": 1784122714
    },
    {
      "name": "미 5년물",
      "symbol": "^FVX",
      "group": "미국채 금리",
      "unit": "%",
      "price": 4.282,
      "prev_close": 4.321,
      "change": -0.0389999999999997,
      "change_pct": -0.9025688498032794,
      "currency": "USD",
      "market_time": 1784122714
    },
    {
      "name": "미 10년물",
      "symbol": "^TNX",
      "group": "미국채 금리",
      "unit": "%",
      "price": 4.565,
      "prev_close": 4.585,
      "change": -0.019999999999999574,
      "change_pct": -0.43620501635767883,
      "currency": "USD",
      "market_time": 1784122714
    },
    {
      "name": "미 30년물",
      "symbol": "^TYX",
      "group": "미국채 금리",
      "unit": "%",
      "price": 5.092,
      "prev_close": 5.094,
      "change": -0.002000000000000668,
      "change_pct": -0.03926187671772022,
      "currency": "USD",
      "market_time": 1784122714
    },
    {
      "name": "달러인덱스(DXY)",
      "symbol": "DX-Y.NYB",
      "group": "매크로",
      "unit": "",
      "price": 100.847,
      "prev_close": 100.919,
      "change": -0.07200000000000273,
      "change_pct": -0.07134434546517775,
      "currency": "USD",
      "market_time": 1784123022
    },
    {
      "name": "VIX 변동성",
      "symbol": "^VIX",
      "group": "매크로",
      "unit": "",
      "price": 16.07,
      "prev_close": 16.5,
      "change": -0.4299999999999997,
      "change_pct": -2.6060606060606046,
      "currency": "USD",
      "market_time": 1784122711
    },
    {
      "name": "금",
      "symbol": "GC=F",
      "group": "원자재",
      "unit": "",
      "price": 4068.3,
      "prev_close": 4061.1,
      "change": 7.200000000000273,
      "change_pct": 0.17729186673562022,
      "currency": "USD",
      "market_time": 1784123024
    },
    {
      "name": "WTI 유가",
      "symbol": "CL=F",
      "group": "원자재",
      "unit": "",
      "price": 80.0,
      "prev_close": 79.34,
      "change": 0.6599999999999966,
      "change_pct": 0.8318628686664944,
      "currency": "USD",
      "market_time": 1784123020
    },
    {
      "name": "코스피",
      "symbol": "KOSPI",
      "group": "한국증시",
      "unit": "",
      "price": 7284.41,
      "prev_close": 6856.83,
      "change": 427.58,
      "change_pct": 6.24,
      "currency": "KRW",
      "market_time": "2026-07-15T18:59:00+09:00"
    },
    {
      "name": "코스닥",
      "symbol": "KOSDAQ",
      "group": "한국증시",
      "unit": "",
      "price": 829.43,
      "prev_close": 783.9799999999999,
      "change": 45.45,
      "change_pct": 5.8,
      "currency": "KRW",
      "market_time": "2026-07-15T18:59:00+09:00"
    }
  ],
  "failures": []
}