{
  "generated_at": "2026-07-16T09:47:11+09:00",
  "exchanges": {
    "upbit": {
      "name": "업비트",
      "vol_24h_krw": 853062051602.44,
      "share_pct": 64.3985
    },
    "bithumb": {
      "name": "빗썸",
      "vol_24h_krw": 381568816067.59,
      "share_pct": 28.805
    },
    "coinone": {
      "name": "코인원",
      "vol_24h_krw": 78662301005.1,
      "share_pct": 5.9383
    },
    "korbit": {
      "name": "코빗",
      "vol_24h_krw": 10579981021.58,
      "share_pct": 0.7987
    },
    "gopax": {
      "name": "고팍스",
      "vol_24h_krw": 789037277.63,
      "share_pct": 0.0596
    }
  },
  "total_vol_krw": 1324662186974.34,
  "kimchi_premium": {
    "btc_pct": -1.7165,
    "note": "업비트 BTC vs Binance BTCUSDT×실외환USD/KRW(frankfurter)"
  },
  "arbitrage": [
    {
      "symbol": "DRV",
      "low_ex": "빗썸",
      "low_price": 206.0,
      "high_ex": "업비트",
      "high_price": 211.0,
      "gap_pct": 2.4272,
      "logo": "https://coin-images.coingecko.com/coins/images/52889/large/Token_Logo.png?1734601695",
      "global_krw": null,
      "kimchi_pct": null,
      "cg_id": "derive",
      "coin_name": "Derive",
      "coin_name_ko": "디라이브",
      "verified": true
    },
    {
      "symbol": "ATH",
      "low_ex": "빗썸",
      "low_price": 6.44,
      "high_ex": "업비트",
      "high_price": 6.59,
      "gap_pct": 2.3133,
      "logo": "https://coin-images.coingecko.com/coins/images/36179/large/logogram_circle_dark_green_vb_green_%281%29.png?1718232706",
      "global_krw": null,
      "kimchi_pct": null,
      "cg_id": "aethir",
      "coin_name": "Aethir",
      "coin_name_ko": "에이셔",
      "verified": true
    },
    {
      "symbol": "VANA",
      "low_ex": "빗썸",
      "low_price": 1982,
      "high_ex": "업비트",
      "high_price": 2027,
      "gap_pct": 2.2704,
      "logo": "https://coin-images.coingecko.com/coins/images/51404/large/vana-logo-200x200.png?1784009862",
      "global_krw": null,
      "kimchi_pct": null,
      "cg_id": "vana",
      "coin_name": "Vana",
      "coin_name_ko": "바나",
      "verified": true
    },
    {
      "symbol": "ARDR",
      "low_ex": "빗썸",
      "low_price": 30.73,
      "high_ex": "업비트",
      "high_price": 31.4,
      "gap_pct": 2.1803,
      "logo": "https://coin-images.coingecko.com/coins/images/525/large/Ardor_Vertical_1.png?1696501746",
      "global_krw": null,
      "kimchi_pct": null,
      "cg_id": "ardor",
      "coin_name": "Ardor",
      "coin_name_ko": "아더",
      "verified": true
    },
    {
      "symbol": "OPG",
      "low_ex": "빗썸",
      "low_price": 161.0,
      "high_ex": "업비트",
      "high_price": 164.0,
      "gap_pct": 1.8634,
      "logo": "https://coin-images.coingecko.com/coins/images/102172863/large/coingecko_logo.png?1776349115",
      "global_krw": null,
      "kimchi_pct": null,
      "cg_id": "opengradient",
      "coin_name": "OpenGradient",
      "coin_name_ko": "오픈그라디언트",
      "verified": true
    },
    {
      "symbol": "BLAST",
      "low_ex": "빗썸",
      "low_price": 0.4429,
      "high_ex": "업비트",
      "high_price": 0.451,
      "gap_pct": 1.8289,
      "logo": "https://coin-images.coingecko.com/coins/images/35494/large/Blast.jpg?1719385662",
      "global_krw": null,
      "kimchi_pct": null,
      "cg_id": "blast",
      "coin_name": "Blast",
      "coin_name_ko": "블라스트",
      "verified": true
    },
    {
      "symbol": "SLX",
      "low_ex": "빗썸",
      "low_price": 171.0,
      "high_ex": "업비트",
      "high_price": 174.0,
      "gap_pct": 1.7544,
      "logo": "https://coin-images.coingecko.com/coins/images/71128/large/slx.png?1779455873",
      "global_krw": null,
      "kimchi_pct": null,
      "cg_id": "solstice",
      "coin_name": "Solstice",
      "coin_name_ko": "솔스티스",
      "verified": true
    },
    {
      "symbol": "ZORA",
      "low_ex": "빗썸",
      "low_price": 10.05,
      "high_ex": "업비트",
      "high_price": 10.2,
      "gap_pct": 1.4925,
      "logo": "https://coin-images.coingecko.com/coins/images/54693/large/zora.jpg?1741094751",
      "global_krw": null,
      "kimchi_pct": null,
      "cg_id": "zora",
      "coin_name": "Zora",
      "coin_name_ko": "조라",
      "verified": true
    },
    {
      "symbol": "PLUME",
      "low_ex": "빗썸",
      "low_price": 14.98,
      "high_ex": "업비트",
      "high_price": 15.2,
      "gap_pct": 1.4686,
      "logo": "https://coin-images.coingecko.com/coins/images/53623/large/plume-token.png?1736896935",
      "global_krw": null,
      "kimchi_pct": null,
      "cg_id": "plume",
      "coin_name": "Plume",
      "coin_name_ko": "플룸",
      "verified": true
    },
    {
      "symbol": "0G",
      "low_ex": "빗썸",
      "low_price": 274.0,
      "high_ex": "업비트",
      "high_price": 278.0,
      "gap_pct": 1.4599,
      "logo": "https://coin-images.coingecko.com/coins/images/69096/large/0G_1024x1024_Circular_Outlined.png?1758637574",
      "global_krw": null,
      "kimchi_pct": null,
      "cg_id": "zero-gravity",
      "coin_name": "0G",
      "coin_name_ko": "제로지",
      "verified": true
    },
    {
      "symbol": "SEI",
      "low_ex": "빗썸",
      "low_price": 69.95,
      "high_ex": "업비트",
      "high_price": 70.9,
      "gap_pct": 1.3581,
      "logo": "https://coin-images.coingecko.com/coins/images/28205/large/Sei_Logo_-_Transparent.png?1696527207",
      "global_krw": null,
      "kimchi_pct": null,
      "cg_id": "sei-network",
      "coin_name": "Sei",
      "coin_name_ko": "세이",
      "verified": true
    },
    {
      "symbol": "ME",
      "low_ex": "빗썸",
      "low_price": 95.63,
      "high_ex": "업비트",
      "high_price": 96.9,
      "gap_pct": 1.328,
      "logo": "https://coin-images.coingecko.com/coins/images/39850/large/_ME_Profile_Dark_2x.png?1734013082",
      "global_krw": null,
      "kimchi_pct": null,
      "cg_id": "magic-eden",
      "coin_name": "Magic Eden",
      "coin_name_ko": "매직에덴",
      "verified": true
    },
    {
      "symbol": "SPX",
      "low_ex": "빗썸",
      "low_price": 542.0,
      "high_ex": "업비트",
      "high_price": 549.0,
      "gap_pct": 1.2915,
      "logo": "https://coin-images.coingecko.com/coins/images/31401/large/centeredcoin_%281%29.png?1737048493",
      "global_krw": null,
      "kimchi_pct": null,
      "cg_id": "spx6900",
      "coin_name": "SPX6900",
      "coin_name_ko": "에스피엑스6900",
      "verified": true
    },
    {
      "symbol": "RE",
      "low_ex": "빗썸",
      "low_price": 704.0,
      "high_ex": "업비트",
      "high_price": 713.0,
      "gap_pct": 1.2784,
      "logo": "https://coin-images.coingecko.com/coins/images/102173708/large/RE-Token.png?1781031591",
      "global_krw": null,
      "kimchi_pct": null,
      "cg_id": "re",
      "coin_name": "Re",
      "coin_name_ko": "리",
      "verified": true
    },
    {
      "symbol": "SOON",
      "low_ex": "빗썸",
      "low_price": 240.0,
      "high_ex": "업비트",
      "high_price": 243.0,
      "gap_pct": 1.25,
      "logo": "https://coin-images.coingecko.com/coins/images/55124/large/red_2.PNG?1743843131",
      "global_krw": null,
      "kimchi_pct": null,
      "cg_id": "soon-2",
      "coin_name": "SOON",
      "coin_name_ko": "쑨",
      "verified": true
    }
  ],
  "volume_top10": [
    {
      "rank": 1,
      "symbol": "USDT",
      "price": 1469,
      "change_pct": 0.0,
      "vol_krw": 129620775335.07,
      "exchange": "빗썸",
      "logo": "https://coin-images.coingecko.com/coins/images/325/large/Tether.png?1696501661",
      "cg_id": "tether",
      "coin_name": "Tether",
      "coin_name_ko": "테더",
      "verified": true,
      "top_exchanges": [
        "bithumb",
        "upbit"
      ]
    },
    {
      "rank": 2,
      "symbol": "ETH",
      "price": 2807000,
      "change_pct": -0.355,
      "vol_krw": 128099558500.44,
      "exchange": "업비트",
      "logo": "https://coin-images.coingecko.com/coins/images/279/large/ethereum.png?1696501628",
      "cg_id": "ethereum",
      "coin_name": "Ethereum",
      "coin_name_ko": "이더리움",
      "verified": true,
      "top_exchanges": [
        "upbit",
        "bithumb"
      ]
    },
    {
      "rank": 3,
      "symbol": "BTC",
      "price": 94680000,
      "change_pct": -0.473,
      "vol_krw": 116433311206.08,
      "exchange": "업비트",
      "logo": "https://coin-images.coingecko.com/coins/images/1/large/bitcoin.png?1696501400",
      "cg_id": "bitcoin",
      "coin_name": "Bitcoin",
      "coin_name_ko": "비트코인",
      "verified": true,
      "top_exchanges": [
        "upbit",
        "bithumb"
      ]
    },
    {
      "rank": 4,
      "symbol": "XRP",
      "price": 1627,
      "change_pct": -0.4893,
      "vol_krw": 100864217543.04,
      "exchange": "업비트",
      "logo": "https://coin-images.coingecko.com/coins/images/44/large/xrp-symbol-white-128.png?1696501442",
      "cg_id": "ripple",
      "coin_name": "XRP",
      "coin_name_ko": "엑스알피(리플)",
      "verified": true,
      "top_exchanges": [
        "upbit",
        "bithumb"
      ]
    },
    {
      "rank": 5,
      "symbol": "XEC",
      "price": 0.00949,
      "change_pct": -2.4666,
      "vol_krw": 47786917622.82,
      "exchange": "업비트",
      "logo": "https://coin-images.coingecko.com/coins/images/16646/large/Logo_final-22.png?1696516207",
      "cg_id": "ecash",
      "coin_name": "eCash",
      "coin_name_ko": "이캐시",
      "verified": true,
      "top_exchanges": [
        "upbit",
        "bithumb"
      ]
    },
    {
      "rank": 6,
      "symbol": "ONDO",
      "price": 528.0,
      "change_pct": -1.4925,
      "vol_krw": 47585366306.27,
      "exchange": "업비트",
      "logo": "https://coin-images.coingecko.com/coins/images/26580/large/ONDO.png?1696525656",
      "cg_id": "ondo-finance",
      "coin_name": "Ondo Finance",
      "coin_name_ko": "온도파이낸스",
      "verified": true,
      "top_exchanges": [
        "upbit",
        "bithumb"
      ]
    },
    {
      "rank": 7,
      "symbol": "B3",
      "price": 1.01,
      "change_pct": 7.906,
      "vol_krw": 37986201612.57,
      "exchange": "업비트",
      "logo": "https://coin-images.coingecko.com/coins/images/54287/large/B3.png?1739001374",
      "cg_id": "b3",
      "coin_name": "B3",
      "coin_name_ko": "비쓰리",
      "verified": true,
      "top_exchanges": [
        "upbit",
        "bithumb"
      ]
    },
    {
      "rank": 8,
      "symbol": "WLD",
      "price": 593.0,
      "change_pct": -2.79,
      "vol_krw": 35906419872.31,
      "exchange": "빗썸",
      "logo": "https://coin-images.coingecko.com/coins/images/31069/large/worldcoin.jpeg?1696529903",
      "cg_id": "worldcoin-wld",
      "coin_name": "Worldcoin",
      "coin_name_ko": "월드코인",
      "verified": true,
      "top_exchanges": [
        "bithumb",
        "upbit"
      ]
    },
    {
      "rank": 9,
      "symbol": "VANA",
      "price": 2027,
      "change_pct": 6.0701,
      "vol_krw": 34590768557.69,
      "exchange": "업비트",
      "logo": "https://coin-images.coingecko.com/coins/images/51404/large/vana-logo-200x200.png?1784009862",
      "cg_id": "vana",
      "coin_name": "Vana",
      "coin_name_ko": "바나",
      "verified": true,
      "top_exchanges": [
        "upbit",
        "bithumb"
      ]
    },
    {
      "rank": 10,
      "symbol": "RLUSD",
      "price": 1470,
      "change_pct": -0.1359,
      "vol_krw": 31783299981.73,
      "exchange": "코인원",
      "logo": "https://coin-images.coingecko.com/coins/images/39651/large/RLUSD_200x200_%281%29.png?1727376633",
      "cg_id": "ripple-usd",
      "coin_name": "Ripple USD",
      "coin_name_ko": null,
      "verified": false,
      "top_exchanges": [
        "coinone"
      ]
    }
  ],
  "gainers_top10": [
    {
      "rank": 1,
      "symbol": "SPURS",
      "price": 294.0,
      "change_pct": 28.95,
      "vol_krw": 2263532003.87,
      "exchange": "빗썸",
      "logo": "https://coin-images.coingecko.com/coins/images/31993/large/SPURS.png",
      "cg_id": "tottenham-hotspur-fc-fan-token",
      "coin_name": "Tottenham Hotspur FC Fan Token",
      "coin_name_ko": null,
      "verified": false,
      "top_exchanges": [
        "bithumb"
      ]
    },
    {
      "rank": 2,
      "symbol": "HOME",
      "price": 24.57,
      "change_pct": 18.87,
      "vol_krw": 5132374587.14,
      "exchange": "빗썸",
      "logo": "https://coin-images.coingecko.com/coins/images/54873/large/defi-app.png?1742235743",
      "cg_id": "home",
      "coin_name": "HOME",
      "coin_name_ko": null,
      "verified": false,
      "top_exchanges": [
        "bithumb"
      ]
    },
    {
      "rank": 3,
      "symbol": "SKL",
      "price": 6.68,
      "change_pct": 12.97,
      "vol_krw": 7187967766.79,
      "exchange": "빗썸",
      "logo": "https://coin-images.coingecko.com/coins/images/13245/large/SKALE_token_300x300.png?1696513021",
      "cg_id": "skale",
      "coin_name": "SKALE",
      "coin_name_ko": null,
      "verified": false,
      "top_exchanges": [
        "bithumb",
        "coinone"
      ]
    },
    {
      "rank": 4,
      "symbol": "CAP",
      "price": 26.52,
      "change_pct": 11.34,
      "vol_krw": 2593149018.72,
      "exchange": "빗썸",
      "logo": "https://coin-images.coingecko.com/coins/images/102174107/large/cap.jpg?1782391237",
      "cg_id": "cap-4",
      "coin_name": "Cap",
      "coin_name_ko": null,
      "verified": false,
      "top_exchanges": [
        "bithumb"
      ]
    },
    {
      "rank": 5,
      "symbol": "ALLO",
      "price": 578.0,
      "change_pct": 9.06,
      "vol_krw": 6367851821.17,
      "exchange": "빗썸",
      "logo": "https://coin-images.coingecko.com/coins/images/70609/large/allo-token.png?1763451165",
      "cg_id": "allora",
      "coin_name": "Allora",
      "coin_name_ko": null,
      "verified": false,
      "top_exchanges": [
        "bithumb"
      ]
    },
    {
      "rank": 6,
      "symbol": "MPLX",
      "price": 41.41,
      "change_pct": 9.03,
      "vol_krw": 9140518385.05,
      "exchange": "빗썸",
      "logo": "https://coin-images.coingecko.com/coins/images/27344/large/mplx.png?1696526391",
      "cg_id": "metaplex",
      "coin_name": "Metaplex",
      "coin_name_ko": null,
      "verified": false,
      "top_exchanges": [
        "bithumb"
      ]
    },
    {
      "rank": 7,
      "symbol": "STOC",
      "price": 688.0,
      "change_pct": 8.8608,
      "vol_krw": 260149779.95,
      "exchange": "고팍스",
      "logo": "https://coin-images.coingecko.com/coins/images/71033/large/Ticker_STRCx__Company_Name_Strategy_PP_Variable__size_200x200.png",
      "cg_id": "strategy-pp-variable-xstock",
      "coin_name": "Strategy PP Variable xStock",
      "coin_name_ko": null,
      "verified": false,
      "top_exchanges": [
        "gopax"
      ]
    },
    {
      "rank": 8,
      "symbol": "B3",
      "price": 1.01,
      "change_pct": 7.906,
      "vol_krw": 37986201612.57,
      "exchange": "업비트",
      "logo": "https://coin-images.coingecko.com/coins/images/54287/large/B3.png?1739001374",
      "cg_id": "b3",
      "coin_name": "B3",
      "coin_name_ko": "비쓰리",
      "verified": true,
      "top_exchanges": [
        "upbit",
        "bithumb"
      ]
    },
    {
      "rank": 9,
      "symbol": "FITFI",
      "price": 0.503,
      "change_pct": 7.69,
      "vol_krw": 301364356.92,
      "exchange": "빗썸",
      "logo": "https://coin-images.coingecko.com/coins/images/25015/large/200x200.png",
      "cg_id": "step-app-fitfi",
      "coin_name": "Step App",
      "coin_name_ko": null,
      "verified": false,
      "top_exchanges": [
        "bithumb"
      ]
    },
    {
      "rank": 10,
      "symbol": "THE",
      "price": 84.69,
      "change_pct": 7.12,
      "vol_krw": 517365924.84,
      "exchange": "빗썸",
      "logo": "https://coin-images.coingecko.com/coins/images/279/large/ethereum.png",
      "cg_id": "ethereum",
      "coin_name": "Ethereum",
      "coin_name_ko": null,
      "verified": false,
      "top_exchanges": [
        "bithumb"
      ]
    }
  ],
  "per_exchange": {
    "upbit": {
      "volume_top10": [
        {
          "rank": 1,
          "symbol": "ETH",
          "price": 2807000,
          "change_pct": -0.355,
          "vol_krw": 92206492775.33,
          "exchange": "업비트",
          "logo": "https://coin-images.coingecko.com/coins/images/279/large/ethereum.png?1696501628",
          "cg_id": "ethereum",
          "coin_name": "Ethereum",
          "coin_name_ko": "이더리움",
          "verified": true
        },
        {
          "rank": 2,
          "symbol": "BTC",
          "price": 94680000,
          "change_pct": -0.473,
          "vol_krw": 81821827306.46,
          "exchange": "업비트",
          "logo": "https://coin-images.coingecko.com/coins/images/1/large/bitcoin.png?1696501400",
          "cg_id": "bitcoin",
          "coin_name": "Bitcoin",
          "coin_name_ko": "비트코인",
          "verified": true
        },
        {
          "rank": 3,
          "symbol": "XRP",
          "price": 1627,
          "change_pct": -0.4893,
          "vol_krw": 68450993440.38,
          "exchange": "업비트",
          "logo": "https://coin-images.coingecko.com/coins/images/44/large/xrp-symbol-white-128.png?1696501442",
          "cg_id": "ripple",
          "coin_name": "XRP",
          "coin_name_ko": "엑스알피(리플)",
          "verified": true
        },
        {
          "rank": 4,
          "symbol": "USDT",
          "price": 1468,
          "change_pct": -0.1361,
          "vol_krw": 45343884575.6,
          "exchange": "업비트",
          "logo": "https://coin-images.coingecko.com/coins/images/325/large/Tether.png?1696501661",
          "cg_id": "tether",
          "coin_name": "Tether",
          "coin_name_ko": "테더",
          "verified": true
        },
        {
          "rank": 5,
          "symbol": "XEC",
          "price": 0.00949,
          "change_pct": -2.4666,
          "vol_krw": 42965817521.55,
          "exchange": "업비트",
          "logo": "https://coin-images.coingecko.com/coins/images/16646/large/Logo_final-22.png?1696516207",
          "cg_id": "ecash",
          "coin_name": "eCash",
          "coin_name_ko": "이캐시",
          "verified": true
        },
        {
          "rank": 6,
          "symbol": "ONDO",
          "price": 528.0,
          "change_pct": -1.4925,
          "vol_krw": 33405462279.75,
          "exchange": "업비트",
          "logo": "https://coin-images.coingecko.com/coins/images/26580/large/ONDO.png?1696525656",
          "cg_id": "ondo-finance",
          "coin_name": "Ondo Finance",
          "coin_name_ko": "온도파이낸스",
          "verified": true
        },
        {
          "rank": 7,
          "symbol": "B3",
          "price": 1.01,
          "change_pct": 7.906,
          "vol_krw": 30762952923.83,
          "exchange": "업비트",
          "logo": "https://coin-images.coingecko.com/coins/images/54287/large/B3.png?1739001374",
          "cg_id": "b3",
          "coin_name": "B3",
          "coin_name_ko": "비쓰리",
          "verified": true
        },
        {
          "rank": 8,
          "symbol": "VANA",
          "price": 2027,
          "change_pct": 6.0701,
          "vol_krw": 29202571317.53,
          "exchange": "업비트",
          "logo": "https://coin-images.coingecko.com/coins/images/51404/large/vana-logo-200x200.png?1784009862",
          "cg_id": "vana",
          "coin_name": "Vana",
          "coin_name_ko": "바나",
          "verified": true
        },
        {
          "rank": 9,
          "symbol": "0G",
          "price": 278.0,
          "change_pct": -2.4561,
          "vol_krw": 22914878097.48,
          "exchange": "업비트",
          "logo": "https://coin-images.coingecko.com/coins/images/69096/large/0G_1024x1024_Circular_Outlined.png?1758637574",
          "cg_id": "zero-gravity",
          "coin_name": "0G",
          "coin_name_ko": "제로지",
          "verified": true
        },
        {
          "rank": 10,
          "symbol": "SLX",
          "price": 174.0,
          "change_pct": -3.8674,
          "vol_krw": 22653924307.62,
          "exchange": "업비트",
          "logo": "https://coin-images.coingecko.com/coins/images/71128/large/slx.png?1779455873",
          "cg_id": "solstice",
          "coin_name": "Solstice",
          "coin_name_ko": "솔스티스",
          "verified": true
        }
      ],
      "gainers_top10": [
        {
          "rank": 1,
          "symbol": "B3",
          "price": 1.01,
          "change_pct": 7.906,
          "vol_krw": 30762952923.83,
          "exchange": "업비트",
          "logo": "https://coin-images.coingecko.com/coins/images/54287/large/B3.png?1739001374",
          "cg_id": "b3",
          "coin_name": "B3",
          "coin_name_ko": "비쓰리",
          "verified": true
        },
        {
          "rank": 2,
          "symbol": "VANA",
          "price": 2027,
          "change_pct": 6.0701,
          "vol_krw": 29202571317.53,
          "exchange": "업비트",
          "logo": "https://coin-images.coingecko.com/coins/images/51404/large/vana-logo-200x200.png?1784009862",
          "cg_id": "vana",
          "coin_name": "Vana",
          "coin_name_ko": "바나",
          "verified": true
        },
        {
          "rank": 3,
          "symbol": "MEGA",
          "price": 74.2,
          "change_pct": 5.0992,
          "vol_krw": 5393344995.73,
          "exchange": "업비트",
          "logo": "https://coin-images.coingecko.com/coins/images/69995/large/9fcb2fa4-b240-46e2-9016-c4f6101a139d.jpeg?1778485816",
          "cg_id": "megaeth",
          "coin_name": "MegaETH",
          "coin_name_ko": "메가이더",
          "verified": true
        },
        {
          "rank": 4,
          "symbol": "DATA",
          "price": 427.0,
          "change_pct": 3.8929,
          "vol_krw": 6659204717.91,
          "exchange": "업비트",
          "logo": "https://coin-images.coingecko.com/coins/images/54035/large/CMC_%281%29.png?1782401376",
          "cg_id": "story-2",
          "coin_name": "Data Network",
          "coin_name_ko": "데이터네트워크",
          "verified": true
        },
        {
          "rank": 5,
          "symbol": "AERGO",
          "price": 34.9,
          "change_pct": 3.5608,
          "vol_krw": 1661548034.4,
          "exchange": "업비트",
          "logo": "https://coin-images.coingecko.com/coins/images/4490/large/aergo.png",
          "cg_id": "aergo",
          "coin_name": "Aergo",
          "coin_name_ko": "아르고",
          "verified": true
        },
        {
          "rank": 6,
          "symbol": "CPOOL",
          "price": 29.6,
          "change_pct": 2.4221,
          "vol_krw": 370508332.25,
          "exchange": "업비트",
          "logo": "https://coin-images.coingecko.com/coins/images/19252/large/photo_2022-08-31_12.45.02.jpeg?1696518697",
          "cg_id": "clearpool",
          "coin_name": "Clearpool",
          "coin_name_ko": "클리어풀",
          "verified": true
        },
        {
          "rank": 7,
          "symbol": "AI",
          "price": 35.3,
          "change_pct": 1.7291,
          "vol_krw": 2253168419.86,
          "exchange": "업비트",
          "logo": "https://coin-images.coingecko.com/coins/images/71027/large/gensyn.png?1765331043",
          "cg_id": "gensyn",
          "coin_name": "Gensyn",
          "coin_name_ko": "젠신",
          "verified": true
        },
        {
          "rank": 8,
          "symbol": "EGLD",
          "price": 4723,
          "change_pct": 1.5699,
          "vol_krw": 1796846148.38,
          "exchange": "업비트",
          "logo": "https://coin-images.coingecko.com/coins/images/12335/large/egld-token-logo.png?1696512162",
          "cg_id": "elrond-erd-2",
          "coin_name": "MultiversX",
          "coin_name_ko": "멀티버스엑스",
          "verified": true
        },
        {
          "rank": 9,
          "symbol": "ATH",
          "price": 6.59,
          "change_pct": 1.2289,
          "vol_krw": 1663674230.51,
          "exchange": "업비트",
          "logo": "https://coin-images.coingecko.com/coins/images/36179/large/logogram_circle_dark_green_vb_green_%281%29.png?1718232706",
          "cg_id": "aethir",
          "coin_name": "Aethir",
          "coin_name_ko": "에이셔",
          "verified": true
        },
        {
          "rank": 10,
          "symbol": "T",
          "price": 6.03,
          "change_pct": 1.1745,
          "vol_krw": 9914203922.66,
          "exchange": "업비트",
          "logo": "https://coin-images.coingecko.com/coins/images/22228/large/nFPNiSbL_400x400.jpg?1696521570",
          "cg_id": "threshold-network-token",
          "coin_name": "Threshold",
          "coin_name_ko": "쓰레스홀드",
          "verified": true
        }
      ]
    },
    "bithumb": {
      "volume_top10": [
        {
          "rank": 1,
          "symbol": "USDT",
          "price": 1469,
          "change_pct": 0.0,
          "vol_krw": 50751740139.62,
          "exchange": "빗썸",
          "logo": "https://coin-images.coingecko.com/coins/images/325/large/Tether.png?1696501661",
          "cg_id": "tether",
          "coin_name": "Tether",
          "coin_name_ko": "테더",
          "verified": true
        },
        {
          "rank": 2,
          "symbol": "ETH",
          "price": 2810000,
          "change_pct": 1.55,
          "vol_krw": 32161489367.52,
          "exchange": "빗썸",
          "logo": "https://coin-images.coingecko.com/coins/images/279/large/ethereum.png?1696501628",
          "cg_id": "ethereum",
          "coin_name": "Ethereum",
          "coin_name_ko": "이더리움",
          "verified": true
        },
        {
          "rank": 3,
          "symbol": "BTC",
          "price": 94808000,
          "change_pct": -0.49,
          "vol_krw": 30402490823.21,
          "exchange": "빗썸",
          "logo": "https://coin-images.coingecko.com/coins/images/1/large/bitcoin.png?1696501400",
          "cg_id": "bitcoin",
          "coin_name": "Bitcoin",
          "coin_name_ko": "비트코인",
          "verified": true
        },
        {
          "rank": 4,
          "symbol": "XRP",
          "price": 1629,
          "change_pct": 0.06,
          "vol_krw": 29050997841.05,
          "exchange": "빗썸",
          "logo": "https://coin-images.coingecko.com/coins/images/44/large/xrp-symbol-white-128.png?1696501442",
          "cg_id": "ripple",
          "coin_name": "XRP",
          "coin_name_ko": "엑스알피(리플)",
          "verified": true
        },
        {
          "rank": 5,
          "symbol": "WLD",
          "price": 593.0,
          "change_pct": -2.79,
          "vol_krw": 18355423864.46,
          "exchange": "빗썸",
          "logo": "https://coin-images.coingecko.com/coins/images/31069/large/worldcoin.jpeg?1696529903",
          "cg_id": "worldcoin-wld",
          "coin_name": "Worldcoin",
          "coin_name_ko": "월드코인",
          "verified": true
        },
        {
          "rank": 6,
          "symbol": "ONDO",
          "price": 529.0,
          "change_pct": 12.55,
          "vol_krw": 13684238923.17,
          "exchange": "빗썸",
          "logo": "https://coin-images.coingecko.com/coins/images/26580/large/ONDO.png?1696525656",
          "cg_id": "ondo-finance",
          "coin_name": "Ondo Finance",
          "coin_name_ko": "온도파이낸스",
          "verified": true
        },
        {
          "rank": 7,
          "symbol": "GNO",
          "price": 167600,
          "change_pct": -55.37,
          "vol_krw": 10072974303.14,
          "exchange": "빗썸",
          "logo": "https://coin-images.coingecko.com/coins/images/662/large/logo_square_simple_300px.png?1696501854",
          "cg_id": "gnosis",
          "coin_name": "Gnosis",
          "coin_name_ko": null,
          "verified": false
        },
        {
          "rank": 8,
          "symbol": "MPLX",
          "price": 41.41,
          "change_pct": 9.03,
          "vol_krw": 9140518385.05,
          "exchange": "빗썸",
          "logo": "https://coin-images.coingecko.com/coins/images/27344/large/mplx.png?1696526391",
          "cg_id": "metaplex",
          "coin_name": "Metaplex",
          "coin_name_ko": null,
          "verified": false
        },
        {
          "rank": 9,
          "symbol": "SOL",
          "price": 112800,
          "change_pct": -1.14,
          "vol_krw": 7462067570.45,
          "exchange": "빗썸",
          "logo": "https://coin-images.coingecko.com/coins/images/4128/large/solana.png?1718769756",
          "cg_id": "solana",
          "coin_name": "Solana",
          "coin_name_ko": "솔라나",
          "verified": true
        },
        {
          "rank": 10,
          "symbol": "B3",
          "price": 1.01,
          "change_pct": 13.95,
          "vol_krw": 7215784116.78,
          "exchange": "빗썸",
          "logo": "https://coin-images.coingecko.com/coins/images/54287/large/B3.png?1739001374",
          "cg_id": "b3",
          "coin_name": "B3",
          "coin_name_ko": "비쓰리",
          "verified": true
        }
      ],
      "gainers_top10": [
        {
          "rank": 1,
          "symbol": "SPURS",
          "price": 294.0,
          "change_pct": 28.95,
          "vol_krw": 2263532003.87,
          "exchange": "빗썸",
          "logo": "https://coin-images.coingecko.com/coins/images/31993/large/SPURS.png",
          "cg_id": "tottenham-hotspur-fc-fan-token",
          "coin_name": "Tottenham Hotspur FC Fan Token",
          "coin_name_ko": null,
          "verified": false
        },
        {
          "rank": 2,
          "symbol": "HOME",
          "price": 24.57,
          "change_pct": 18.87,
          "vol_krw": 5132374587.14,
          "exchange": "빗썸",
          "logo": "https://coin-images.coingecko.com/coins/images/54873/large/defi-app.png?1742235743",
          "cg_id": "home",
          "coin_name": "HOME",
          "coin_name_ko": null,
          "verified": false
        },
        {
          "rank": 3,
          "symbol": "B3",
          "price": 1.01,
          "change_pct": 13.95,
          "vol_krw": 7215784116.78,
          "exchange": "빗썸",
          "logo": "https://coin-images.coingecko.com/coins/images/54287/large/B3.png?1739001374",
          "cg_id": "b3",
          "coin_name": "B3",
          "coin_name_ko": "비쓰리",
          "verified": true
        },
        {
          "rank": 4,
          "symbol": "XEC",
          "price": 0.0095,
          "change_pct": 13.1,
          "vol_krw": 4785206201.33,
          "exchange": "빗썸",
          "logo": "https://coin-images.coingecko.com/coins/images/16646/large/Logo_final-22.png?1696516207",
          "cg_id": "ecash",
          "coin_name": "eCash",
          "coin_name_ko": "이캐시",
          "verified": true
        },
        {
          "rank": 5,
          "symbol": "SKL",
          "price": 6.68,
          "change_pct": 12.97,
          "vol_krw": 7180393792.19,
          "exchange": "빗썸",
          "logo": "https://coin-images.coingecko.com/coins/images/13245/large/SKALE_token_300x300.png?1696513021",
          "cg_id": "skale",
          "coin_name": "SKALE",
          "coin_name_ko": null,
          "verified": false
        },
        {
          "rank": 6,
          "symbol": "ONDO",
          "price": 529.0,
          "change_pct": 12.55,
          "vol_krw": 13684238923.17,
          "exchange": "빗썸",
          "logo": "https://coin-images.coingecko.com/coins/images/26580/large/ONDO.png?1696525656",
          "cg_id": "ondo-finance",
          "coin_name": "Ondo Finance",
          "coin_name_ko": "온도파이낸스",
          "verified": true
        },
        {
          "rank": 7,
          "symbol": "ETHFI",
          "price": 641.0,
          "change_pct": 11.87,
          "vol_krw": 234897521.65,
          "exchange": "빗썸",
          "logo": "https://coin-images.coingecko.com/coins/images/35958/large/etherfi.jpeg?1710254562",
          "cg_id": "ether-fi",
          "coin_name": "Ether.fi",
          "coin_name_ko": "이더파이",
          "verified": true
        },
        {
          "rank": 8,
          "symbol": "CAP",
          "price": 26.52,
          "change_pct": 11.34,
          "vol_krw": 2593149018.72,
          "exchange": "빗썸",
          "logo": "https://coin-images.coingecko.com/coins/images/102174107/large/cap.jpg?1782391237",
          "cg_id": "cap-4",
          "coin_name": "Cap",
          "coin_name_ko": null,
          "verified": false
        },
        {
          "rank": 9,
          "symbol": "PUMP",
          "price": 2.44,
          "change_pct": 11.14,
          "vol_krw": 719048919.06,
          "exchange": "빗썸",
          "logo": "https://coin-images.coingecko.com/coins/images/67164/large/pump.jpg?1751949376",
          "cg_id": "pump-fun",
          "coin_name": "Pump.fun",
          "coin_name_ko": "펌프펀",
          "verified": true
        },
        {
          "rank": 10,
          "symbol": "FLOCK",
          "price": 51.12,
          "change_pct": 10.51,
          "vol_krw": 2693670932.52,
          "exchange": "빗썸",
          "logo": "https://coin-images.coingecko.com/coins/images/53178/large/FLock_Token_Logo.png?1735561398",
          "cg_id": "flock-2",
          "coin_name": "FLock.io",
          "coin_name_ko": "플록",
          "verified": true
        }
      ]
    },
    "coinone": {
      "volume_top10": [
        {
          "rank": 1,
          "symbol": "RLUSD",
          "price": 1470,
          "change_pct": -0.1359,
          "vol_krw": 31783299981.73,
          "exchange": "코인원",
          "logo": "https://coin-images.coingecko.com/coins/images/39651/large/RLUSD_200x200_%281%29.png?1727376633",
          "cg_id": "ripple-usd",
          "coin_name": "Ripple USD",
          "coin_name_ko": null,
          "verified": false
        },
        {
          "rank": 2,
          "symbol": "USDT",
          "price": 1468,
          "change_pct": -0.1361,
          "vol_krw": 26414331702.88,
          "exchange": "코인원",
          "logo": "https://coin-images.coingecko.com/coins/images/325/large/Tether.png?1696501661",
          "cg_id": "tether",
          "coin_name": "Tether",
          "coin_name_ko": "테더",
          "verified": true
        },
        {
          "rank": 3,
          "symbol": "USDC",
          "price": 1469,
          "change_pct": -0.136,
          "vol_krw": 6481264492.28,
          "exchange": "코인원",
          "logo": "https://coin-images.coingecko.com/coins/images/6319/large/USDC.png?1769615602",
          "cg_id": "usd-coin",
          "coin_name": "USD Coin",
          "coin_name_ko": "유에스디코인",
          "verified": true
        },
        {
          "rank": 4,
          "symbol": "BTC",
          "price": 94790000,
          "change_pct": -0.4725,
          "vol_krw": 3337624256.44,
          "exchange": "코인원",
          "logo": "https://coin-images.coingecko.com/coins/images/1/large/bitcoin.png?1696501400",
          "cg_id": "bitcoin",
          "coin_name": "Bitcoin",
          "coin_name_ko": "비트코인",
          "verified": true
        },
        {
          "rank": 5,
          "symbol": "ETH",
          "price": 2807000,
          "change_pct": 1.519,
          "vol_krw": 2768406744.16,
          "exchange": "코인원",
          "logo": "https://coin-images.coingecko.com/coins/images/279/large/ethereum.png?1696501628",
          "cg_id": "ethereum",
          "coin_name": "Ethereum",
          "coin_name_ko": "이더리움",
          "verified": true
        },
        {
          "rank": 6,
          "symbol": "XRP",
          "price": 1628,
          "change_pct": 0.0,
          "vol_krw": 2219432948.26,
          "exchange": "코인원",
          "logo": "https://coin-images.coingecko.com/coins/images/44/large/xrp-symbol-white-128.png?1696501442",
          "cg_id": "ripple",
          "coin_name": "XRP",
          "coin_name_ko": "엑스알피(리플)",
          "verified": true
        },
        {
          "rank": 7,
          "symbol": "WLD",
          "price": 592.5,
          "change_pct": -2.5493,
          "vol_krw": 781496458.46,
          "exchange": "코인원",
          "logo": "https://coin-images.coingecko.com/coins/images/31069/large/worldcoin.jpeg?1696529903",
          "cg_id": "worldcoin-wld",
          "coin_name": "Worldcoin",
          "coin_name_ko": "월드코인",
          "verified": true
        },
        {
          "rank": 8,
          "symbol": "SOL",
          "price": 112800,
          "change_pct": -1.1394,
          "vol_krw": 704643330.95,
          "exchange": "코인원",
          "logo": "https://coin-images.coingecko.com/coins/images/4128/large/solana.png?1718769756",
          "cg_id": "solana",
          "coin_name": "Solana",
          "coin_name_ko": "솔라나",
          "verified": true
        },
        {
          "rank": 9,
          "symbol": "XLM",
          "price": 275.9,
          "change_pct": 1.9963,
          "vol_krw": 573695462.15,
          "exchange": "코인원",
          "logo": "https://coin-images.coingecko.com/coins/images/100/large/fmpFRHHQ_400x400.jpg",
          "cg_id": "stellar",
          "coin_name": "Lumen",
          "coin_name_ko": "스텔라루멘",
          "verified": false
        },
        {
          "rank": 10,
          "symbol": "ONDO",
          "price": 527.5,
          "change_pct": 12.3775,
          "vol_krw": 448425878.81,
          "exchange": "코인원",
          "logo": "https://coin-images.coingecko.com/coins/images/26580/large/ONDO.png?1696525656",
          "cg_id": "ondo-finance",
          "coin_name": "Ondo Finance",
          "coin_name_ko": "온도파이낸스",
          "verified": true
        }
      ],
      "gainers_top10": [
        {
          "rank": 1,
          "symbol": "ONDO",
          "price": 527.5,
          "change_pct": 12.3775,
          "vol_krw": 448425878.81,
          "exchange": "코인원",
          "logo": "https://coin-images.coingecko.com/coins/images/26580/large/ONDO.png?1696525656",
          "cg_id": "ondo-finance",
          "coin_name": "Ondo Finance",
          "coin_name_ko": "온도파이낸스",
          "verified": true
        },
        {
          "rank": 2,
          "symbol": "PENGU",
          "price": 9.11,
          "change_pct": 4.0548,
          "vol_krw": 282899764.56,
          "exchange": "코인원",
          "logo": "https://coin-images.coingecko.com/coins/images/52622/large/PUDGY_PENGUINS_PENGU_PFP.png?1733809110",
          "cg_id": "pudgy-penguins",
          "coin_name": "Pudgy Penguins",
          "coin_name_ko": "펏지펭귄",
          "verified": true
        },
        {
          "rank": 3,
          "symbol": "RIVER",
          "price": 4870,
          "change_pct": 2.0109,
          "vol_krw": 193985059.85,
          "exchange": "코인원",
          "logo": "https://coin-images.coingecko.com/coins/images/69318/large/river-token.png?1758523089",
          "cg_id": "river",
          "coin_name": "River",
          "coin_name_ko": null,
          "verified": false
        },
        {
          "rank": 4,
          "symbol": "XLM",
          "price": 275.9,
          "change_pct": 1.9963,
          "vol_krw": 573695462.15,
          "exchange": "코인원",
          "logo": "https://coin-images.coingecko.com/coins/images/100/large/fmpFRHHQ_400x400.jpg",
          "cg_id": "stellar",
          "coin_name": "Lumen",
          "coin_name_ko": "스텔라루멘",
          "verified": false
        },
        {
          "rank": 5,
          "symbol": "ETH",
          "price": 2807000,
          "change_pct": 1.519,
          "vol_krw": 2768406744.16,
          "exchange": "코인원",
          "logo": "https://coin-images.coingecko.com/coins/images/279/large/ethereum.png?1696501628",
          "cg_id": "ethereum",
          "coin_name": "Ethereum",
          "coin_name_ko": "이더리움",
          "verified": true
        },
        {
          "rank": 6,
          "symbol": "SHIB",
          "price": 0.0062,
          "change_pct": 0.0,
          "vol_krw": 136111312.66,
          "exchange": "코인원",
          "logo": "https://coin-images.coingecko.com/coins/images/11939/large/shiba.png?1696511800",
          "cg_id": "shiba-inu",
          "coin_name": "Shiba Inu",
          "coin_name_ko": "시바이누",
          "verified": true
        },
        {
          "rank": 7,
          "symbol": "PEPE",
          "price": 0.0041,
          "change_pct": 0.0,
          "vol_krw": 147337648.74,
          "exchange": "코인원",
          "logo": "https://coin-images.coingecko.com/coins/images/29850/large/pepe-token.jpeg?1696528776",
          "cg_id": "pepe",
          "coin_name": "Pepe",
          "coin_name_ko": "페페",
          "verified": true
        },
        {
          "rank": 8,
          "symbol": "XRP",
          "price": 1628,
          "change_pct": 0.0,
          "vol_krw": 2219432948.26,
          "exchange": "코인원",
          "logo": "https://coin-images.coingecko.com/coins/images/44/large/xrp-symbol-white-128.png?1696501442",
          "cg_id": "ripple",
          "coin_name": "XRP",
          "coin_name_ko": "엑스알피(리플)",
          "verified": true
        },
        {
          "rank": 9,
          "symbol": "RLUSD",
          "price": 1470,
          "change_pct": -0.1359,
          "vol_krw": 31783299981.73,
          "exchange": "코인원",
          "logo": "https://coin-images.coingecko.com/coins/images/39651/large/RLUSD_200x200_%281%29.png?1727376633",
          "cg_id": "ripple-usd",
          "coin_name": "Ripple USD",
          "coin_name_ko": null,
          "verified": false
        },
        {
          "rank": 10,
          "symbol": "USDC",
          "price": 1469,
          "change_pct": -0.136,
          "vol_krw": 6481264492.28,
          "exchange": "코인원",
          "logo": "https://coin-images.coingecko.com/coins/images/6319/large/USDC.png?1769615602",
          "cg_id": "usd-coin",
          "coin_name": "USD Coin",
          "coin_name_ko": "유에스디코인",
          "verified": true
        }
      ]
    },
    "korbit": {
      "volume_top10": [
        {
          "rank": 1,
          "symbol": "USDT",
          "price": 1468,
          "change_pct": -0.14,
          "vol_krw": 6872928908.72,
          "exchange": "코빗",
          "logo": "https://coin-images.coingecko.com/coins/images/325/large/Tether.png?1696501661",
          "cg_id": "tether",
          "coin_name": "Tether",
          "coin_name_ko": "테더",
          "verified": true
        },
        {
          "rank": 2,
          "symbol": "XRP",
          "price": 1628,
          "change_pct": 0.06,
          "vol_krw": 1100067717.71,
          "exchange": "코빗",
          "logo": "https://coin-images.coingecko.com/coins/images/44/large/xrp-symbol-white-128.png?1696501442",
          "cg_id": "ripple",
          "coin_name": "XRP",
          "coin_name_ko": "엑스알피(리플)",
          "verified": true
        },
        {
          "rank": 3,
          "symbol": "ETH",
          "price": 2810000,
          "change_pct": 1.77,
          "vol_krw": 953870916.47,
          "exchange": "코빗",
          "logo": "https://coin-images.coingecko.com/coins/images/279/large/ethereum.png?1696501628",
          "cg_id": "ethereum",
          "coin_name": "Ethereum",
          "coin_name_ko": "이더리움",
          "verified": true
        },
        {
          "rank": 4,
          "symbol": "BTC",
          "price": 94786000,
          "change_pct": -0.44,
          "vol_krw": 861174729.09,
          "exchange": "코빗",
          "logo": "https://coin-images.coingecko.com/coins/images/1/large/bitcoin.png?1696501400",
          "cg_id": "bitcoin",
          "coin_name": "Bitcoin",
          "coin_name_ko": "비트코인",
          "verified": true
        },
        {
          "rank": 5,
          "symbol": "WLD",
          "price": 593.4,
          "change_pct": -2.35,
          "vol_krw": 176275554.62,
          "exchange": "코빗",
          "logo": "https://coin-images.coingecko.com/coins/images/31069/large/worldcoin.jpeg?1696529903",
          "cg_id": "worldcoin-wld",
          "coin_name": "Worldcoin",
          "coin_name_ko": "월드코인",
          "verified": true
        },
        {
          "rank": 6,
          "symbol": "SOL",
          "price": 112800,
          "change_pct": -1.05,
          "vol_krw": 162347540.99,
          "exchange": "코빗",
          "logo": "https://coin-images.coingecko.com/coins/images/4128/large/solana.png?1718769756",
          "cg_id": "solana",
          "coin_name": "Solana",
          "coin_name_ko": "솔라나",
          "verified": true
        },
        {
          "rank": 7,
          "symbol": "XLM",
          "price": 276.0,
          "change_pct": 2.15,
          "vol_krw": 78814940.27,
          "exchange": "코빗",
          "logo": "https://coin-images.coingecko.com/coins/images/100/large/fmpFRHHQ_400x400.jpg",
          "cg_id": "stellar",
          "coin_name": "Lumen",
          "coin_name_ko": "스텔라루멘",
          "verified": false
        },
        {
          "rank": 8,
          "symbol": "USDC",
          "price": 1470,
          "change_pct": -0.07,
          "vol_krw": 53838773.16,
          "exchange": "코빗",
          "logo": "https://coin-images.coingecko.com/coins/images/6319/large/USDC.png?1769615602",
          "cg_id": "usd-coin",
          "coin_name": "USD Coin",
          "coin_name_ko": "유에스디코인",
          "verified": true
        },
        {
          "rank": 9,
          "symbol": "ONDO",
          "price": 528.0,
          "change_pct": 14.53,
          "vol_krw": 47239224.54,
          "exchange": "코빗",
          "logo": "https://coin-images.coingecko.com/coins/images/26580/large/ONDO.png?1696525656",
          "cg_id": "ondo-finance",
          "coin_name": "Ondo Finance",
          "coin_name_ko": "온도파이낸스",
          "verified": true
        },
        {
          "rank": 10,
          "symbol": "DOGE",
          "price": 108.5,
          "change_pct": -0.28,
          "vol_krw": 44771693.91,
          "exchange": "코빗",
          "logo": "https://coin-images.coingecko.com/coins/images/5/large/dogecoin.png?1696501409",
          "cg_id": "dogecoin",
          "coin_name": "Dogecoin",
          "coin_name_ko": "도지코인",
          "verified": true
        }
      ],
      "gainers_top10": [
        {
          "rank": 1,
          "symbol": "ETH",
          "price": 2810000,
          "change_pct": 1.77,
          "vol_krw": 953870916.47,
          "exchange": "코빗",
          "logo": "https://coin-images.coingecko.com/coins/images/279/large/ethereum.png?1696501628",
          "cg_id": "ethereum",
          "coin_name": "Ethereum",
          "coin_name_ko": "이더리움",
          "verified": true
        },
        {
          "rank": 2,
          "symbol": "XRP",
          "price": 1628,
          "change_pct": 0.06,
          "vol_krw": 1100067717.71,
          "exchange": "코빗",
          "logo": "https://coin-images.coingecko.com/coins/images/44/large/xrp-symbol-white-128.png?1696501442",
          "cg_id": "ripple",
          "coin_name": "XRP",
          "coin_name_ko": "엑스알피(리플)",
          "verified": true
        },
        {
          "rank": 3,
          "symbol": "USDT",
          "price": 1468,
          "change_pct": -0.14,
          "vol_krw": 6872928908.72,
          "exchange": "코빗",
          "logo": "https://coin-images.coingecko.com/coins/images/325/large/Tether.png?1696501661",
          "cg_id": "tether",
          "coin_name": "Tether",
          "coin_name_ko": "테더",
          "verified": true
        },
        {
          "rank": 4,
          "symbol": "BTC",
          "price": 94786000,
          "change_pct": -0.44,
          "vol_krw": 861174729.09,
          "exchange": "코빗",
          "logo": "https://coin-images.coingecko.com/coins/images/1/large/bitcoin.png?1696501400",
          "cg_id": "bitcoin",
          "coin_name": "Bitcoin",
          "coin_name_ko": "비트코인",
          "verified": true
        },
        {
          "rank": 5,
          "symbol": "SOL",
          "price": 112800,
          "change_pct": -1.05,
          "vol_krw": 162347540.99,
          "exchange": "코빗",
          "logo": "https://coin-images.coingecko.com/coins/images/4128/large/solana.png?1718769756",
          "cg_id": "solana",
          "coin_name": "Solana",
          "coin_name_ko": "솔라나",
          "verified": true
        },
        {
          "rank": 6,
          "symbol": "WLD",
          "price": 593.4,
          "change_pct": -2.35,
          "vol_krw": 176275554.62,
          "exchange": "코빗",
          "logo": "https://coin-images.coingecko.com/coins/images/31069/large/worldcoin.jpeg?1696529903",
          "cg_id": "worldcoin-wld",
          "coin_name": "Worldcoin",
          "coin_name_ko": "월드코인",
          "verified": true
        }
      ]
    },
    "gopax": {
      "volume_top10": [
        {
          "rank": 1,
          "symbol": "STOC",
          "price": 688.0,
          "change_pct": 8.8608,
          "vol_krw": 260149779.95,
          "exchange": "고팍스",
          "logo": "https://coin-images.coingecko.com/coins/images/71033/large/Ticker_STRCx__Company_Name_Strategy_PP_Variable__size_200x200.png",
          "cg_id": "strategy-pp-variable-xstock",
          "coin_name": "Strategy PP Variable xStock",
          "coin_name_ko": null,
          "verified": false
        },
        {
          "rank": 2,
          "symbol": "USDT",
          "price": 1469,
          "change_pct": -0.068,
          "vol_krw": 237890008.24,
          "exchange": "고팍스",
          "logo": "https://coin-images.coingecko.com/coins/images/325/large/Tether.png?1696501661",
          "cg_id": "tether",
          "coin_name": "Tether",
          "coin_name_ko": "테더",
          "verified": true
        },
        {
          "rank": 3,
          "symbol": "EGGT",
          "price": 443.0,
          "change_pct": -2.8509,
          "vol_krw": 45337486.39,
          "exchange": "고팍스",
          "logo": null,
          "cg_id": null,
          "coin_name": null,
          "coin_name_ko": null,
          "verified": false
        },
        {
          "rank": 4,
          "symbol": "LOCUS",
          "price": 10.0,
          "change_pct": 0.3009,
          "vol_krw": 44058781.9,
          "exchange": "고팍스",
          "logo": "https://coin-images.coingecko.com/coins/images/6903/large/32169759_2050428658545017_7287666225423843328_n.jpg",
          "cg_id": "locus-chain",
          "coin_name": "Locus Chain",
          "coin_name_ko": null,
          "verified": false
        },
        {
          "rank": 5,
          "symbol": "XRP",
          "price": 1626,
          "change_pct": -0.8537,
          "vol_krw": 42725595.64,
          "exchange": "고팍스",
          "logo": "https://coin-images.coingecko.com/coins/images/44/large/xrp-symbol-white-128.png?1696501442",
          "cg_id": "ripple",
          "coin_name": "XRP",
          "coin_name_ko": "엑스알피(리플)",
          "verified": true
        },
        {
          "rank": 6,
          "symbol": "MTHT",
          "price": 993.0,
          "change_pct": 0.2018,
          "vol_krw": 16779384.51,
          "exchange": "고팍스",
          "logo": null,
          "cg_id": null,
          "coin_name": null,
          "coin_name_ko": null,
          "verified": false
        },
        {
          "rank": 7,
          "symbol": "SOL",
          "price": 115900,
          "change_pct": 1.3998,
          "vol_krw": 16518411.53,
          "exchange": "고팍스",
          "logo": "https://coin-images.coingecko.com/coins/images/4128/large/solana.png?1718769756",
          "cg_id": "solana",
          "coin_name": "Solana",
          "coin_name_ko": "솔라나",
          "verified": true
        },
        {
          "rank": 8,
          "symbol": "CLE",
          "price": 9.34,
          "change_pct": 0.6466,
          "vol_krw": 14867500.64,
          "exchange": "고팍스",
          "logo": "https://coin-images.coingecko.com/coins/images/51054/large/Hashnote_SDYC_200x200.png",
          "cg_id": "hashnote-usyc",
          "coin_name": "Circle USYC",
          "coin_name_ko": null,
          "verified": false
        },
        {
          "rank": 9,
          "symbol": "CRETA",
          "price": 3.96,
          "change_pct": 3.6649,
          "vol_krw": 13989329.1,
          "exchange": "고팍스",
          "logo": "https://coin-images.coingecko.com/coins/images/29129/large/colour_icon.png",
          "cg_id": "creta-world",
          "coin_name": "Creta World",
          "coin_name_ko": null,
          "verified": false
        },
        {
          "rank": 10,
          "symbol": "XRUN",
          "price": 72.2,
          "change_pct": 0.2778,
          "vol_krw": 13690639.37,
          "exchange": "고팍스",
          "logo": "https://coin-images.coingecko.com/coins/images/25272/large/19787.png",
          "cg_id": "xrun",
          "coin_name": "XRun",
          "coin_name_ko": null,
          "verified": false
        }
      ],
      "gainers_top10": [
        {
          "rank": 1,
          "symbol": "STOC",
          "price": 688.0,
          "change_pct": 8.8608,
          "vol_krw": 260149779.95,
          "exchange": "고팍스",
          "logo": "https://coin-images.coingecko.com/coins/images/71033/large/Ticker_STRCx__Company_Name_Strategy_PP_Variable__size_200x200.png",
          "cg_id": "strategy-pp-variable-xstock",
          "coin_name": "Strategy PP Variable xStock",
          "coin_name_ko": null,
          "verified": false
        },
        {
          "rank": 2,
          "symbol": "USDT",
          "price": 1469,
          "change_pct": -0.068,
          "vol_krw": 237890008.24,
          "exchange": "고팍스",
          "logo": "https://coin-images.coingecko.com/coins/images/325/large/Tether.png?1696501661",
          "cg_id": "tether",
          "coin_name": "Tether",
          "coin_name_ko": "테더",
          "verified": true
        }
      ]
    }
  }
}