{
  "generated_at": "2026-06-25T04:43:32+09:00",
  "exchanges": {
    "upbit": {
      "name": "업비트",
      "vol_24h_krw": 1312551965210.04,
      "share_pct": 64.0822
    },
    "bithumb": {
      "name": "빗썸",
      "vol_24h_krw": 627510672684.25,
      "share_pct": 30.6367
    },
    "coinone": {
      "name": "코인원",
      "vol_24h_krw": 88192628891.21,
      "share_pct": 4.3058
    },
    "korbit": {
      "name": "코빗",
      "vol_24h_krw": 18841450589.42,
      "share_pct": 0.9199
    },
    "gopax": {
      "name": "고팍스",
      "vol_24h_krw": 1136564365.31,
      "share_pct": 0.0555
    }
  },
  "total_vol_krw": 2048233281740.23,
  "kimchi_premium": {
    "btc_pct": -1.2183,
    "note": "업비트 BTC vs Binance BTCUSDT×실외환USD/KRW(frankfurter)"
  },
  "arbitrage": [
    {
      "symbol": "H",
      "low_ex": "코인원",
      "low_price": 114.3,
      "high_ex": "빗썸",
      "high_price": 143.0,
      "gap_pct": 25.1094,
      "logo": "https://coin-images.coingecko.com/coins/images/66811/large/H_tokenLogo_original.png?1750581252",
      "global_krw": 115.94,
      "kimchi_pct": 23.3358
    },
    {
      "symbol": "MMT",
      "low_ex": "빗썸",
      "low_price": 273.0,
      "high_ex": "업비트",
      "high_price": 280.0,
      "gap_pct": 2.5641,
      "logo": "https://coin-images.coingecko.com/coins/images/69899/large/4_icon_PFP_RGB.png",
      "global_krw": null,
      "kimchi_pct": null
    },
    {
      "symbol": "WCT",
      "low_ex": "빗썸",
      "low_price": 61.99,
      "high_ex": "업비트",
      "high_price": 63.2,
      "gap_pct": 1.9519,
      "logo": null,
      "global_krw": null,
      "kimchi_pct": null
    },
    {
      "symbol": "MED",
      "low_ex": "빗썸",
      "low_price": 2.11,
      "high_ex": "업비트",
      "high_price": 2.15,
      "gap_pct": 1.8957,
      "logo": null,
      "global_krw": null,
      "kimchi_pct": null
    },
    {
      "symbol": "CBK",
      "low_ex": "빗썸",
      "low_price": 265.0,
      "high_ex": "업비트",
      "high_price": 270.0,
      "gap_pct": 1.8868,
      "logo": null,
      "global_krw": null,
      "kimchi_pct": null
    },
    {
      "symbol": "BREV",
      "low_ex": "빗썸",
      "low_price": 109.0,
      "high_ex": "업비트",
      "high_price": 111.0,
      "gap_pct": 1.8349,
      "logo": "https://coin-images.coingecko.com/coins/images/71219/large/brevis-circle_200x200.png",
      "global_krw": null,
      "kimchi_pct": null
    },
    {
      "symbol": "ETHFI",
      "low_ex": "빗썸",
      "low_price": 493.0,
      "high_ex": "업비트",
      "high_price": 502.0,
      "gap_pct": 1.8256,
      "logo": "https://coin-images.coingecko.com/coins/images/35958/large/etherfi.jpeg?1710254562",
      "global_krw": 507.38,
      "kimchi_pct": -1.0605
    },
    {
      "symbol": "KITE",
      "low_ex": "빗썸",
      "low_price": 222.0,
      "high_ex": "업비트",
      "high_price": 226.0,
      "gap_pct": 1.8018,
      "logo": "https://coin-images.coingecko.com/coins/images/70426/large/KITE-ICON.png?1762328605",
      "global_krw": 227.95,
      "kimchi_pct": -0.8561
    },
    {
      "symbol": "CARV",
      "low_ex": "빗썸",
      "low_price": 48.38,
      "high_ex": "업비트",
      "high_price": 49.2,
      "gap_pct": 1.6949,
      "logo": null,
      "global_krw": null,
      "kimchi_pct": null
    },
    {
      "symbol": "NXPC",
      "low_ex": "빗썸",
      "low_price": 428.0,
      "high_ex": "업비트",
      "high_price": 435.0,
      "gap_pct": 1.6355,
      "logo": "https://coin-images.coingecko.com/coins/images/55703/large/wk63iOZz_400x400.png?1747126039",
      "global_krw": 438.79,
      "kimchi_pct": -0.8641
    },
    {
      "symbol": "SPX",
      "low_ex": "빗썸",
      "low_price": 492.0,
      "high_ex": "업비트",
      "high_price": 500.0,
      "gap_pct": 1.626,
      "logo": "https://coin-images.coingecko.com/coins/images/31401/large/centeredcoin_%281%29.png?1737048493",
      "global_krw": 504.69,
      "kimchi_pct": -0.9283
    },
    {
      "symbol": "MEW",
      "low_ex": "빗썸",
      "low_price": 0.5009,
      "high_ex": "업비트",
      "high_price": 0.509,
      "gap_pct": 1.6171,
      "logo": null,
      "global_krw": null,
      "kimchi_pct": null
    },
    {
      "symbol": "BLEND",
      "low_ex": "빗썸",
      "low_price": 80.41,
      "high_ex": "업비트",
      "high_price": 81.7,
      "gap_pct": 1.6043,
      "logo": null,
      "global_krw": null,
      "kimchi_pct": null
    },
    {
      "symbol": "SIGN",
      "low_ex": "빗썸",
      "low_price": 12.21,
      "high_ex": "업비트",
      "high_price": 12.4,
      "gap_pct": 1.5561,
      "logo": null,
      "global_krw": null,
      "kimchi_pct": null
    },
    {
      "symbol": "ONG",
      "low_ex": "빗썸",
      "low_price": 69.23,
      "high_ex": "업비트",
      "high_price": 70.3,
      "gap_pct": 1.5456,
      "logo": "https://coin-images.coingecko.com/coins/images/5716/large/ONG_logo.png",
      "global_krw": null,
      "kimchi_pct": null
    }
  ],
  "volume_top10": [
    {
      "rank": 1,
      "symbol": "BTC",
      "price": 91300000,
      "change_pct": -3.376,
      "vol_krw": 172825409902.31,
      "exchange": "업비트",
      "logo": "https://coin-images.coingecko.com/coins/images/1/large/bitcoin.png?1696501400"
    },
    {
      "rank": 2,
      "symbol": "XRP",
      "price": 1610,
      "change_pct": -3.7657,
      "vol_krw": 138240973128.96,
      "exchange": "업비트",
      "logo": "https://coin-images.coingecko.com/coins/images/44/large/xrp-symbol-white-128.png?1696501442"
    },
    {
      "rank": 3,
      "symbol": "USDT",
      "price": 1526,
      "change_pct": 1.06,
      "vol_krw": 82286692509.91,
      "exchange": "빗썸",
      "logo": "https://coin-images.coingecko.com/coins/images/325/large/Tether.png?1696501661"
    },
    {
      "rank": 4,
      "symbol": "USDT",
      "price": 1527,
      "change_pct": 1.3271,
      "vol_krw": 80518148605.23,
      "exchange": "업비트",
      "logo": "https://coin-images.coingecko.com/coins/images/325/large/Tether.png?1696501661"
    },
    {
      "rank": 5,
      "symbol": "WLD",
      "price": 784.0,
      "change_pct": -4.3902,
      "vol_krw": 78915447198.43,
      "exchange": "업비트",
      "logo": "https://coin-images.coingecko.com/coins/images/31069/large/worldcoin.jpeg?1696529903"
    },
    {
      "rank": 6,
      "symbol": "WLD",
      "price": 785.0,
      "change_pct": -3.68,
      "vol_krw": 76541770577.92,
      "exchange": "빗썸",
      "logo": "https://coin-images.coingecko.com/coins/images/31069/large/worldcoin.jpeg?1696529903"
    },
    {
      "rank": 7,
      "symbol": "ETH",
      "price": 2411000,
      "change_pct": -4.0971,
      "vol_krw": 73053344363.37,
      "exchange": "업비트",
      "logo": "https://coin-images.coingecko.com/coins/images/279/large/ethereum.png?1696501628"
    },
    {
      "rank": 8,
      "symbol": "SLX",
      "price": 403.0,
      "change_pct": 16.474,
      "vol_krw": 67778507503.4,
      "exchange": "업비트",
      "logo": "https://coin-images.coingecko.com/coins/images/71128/large/slx.png?1779455873"
    },
    {
      "rank": 9,
      "symbol": "ARX",
      "price": 397.0,
      "change_pct": -19.9597,
      "vol_krw": 67379308806.59,
      "exchange": "업비트",
      "logo": "https://coin-images.coingecko.com/coins/images/54948/large/Arcium_Logomark_04_400x400_circle.png?1782278429"
    },
    {
      "rank": 10,
      "symbol": "ID",
      "price": 58.6,
      "change_pct": 16.0396,
      "vol_krw": 56666621199.24,
      "exchange": "업비트",
      "logo": "https://coin-images.coingecko.com/coins/images/50882/large/hyperliquid.jpg"
    }
  ],
  "gainers_top10": [
    {
      "rank": 1,
      "symbol": "SLX",
      "price": 398.0,
      "change_pct": 31.35,
      "vol_krw": 23568803866.03,
      "exchange": "빗썸",
      "logo": "https://coin-images.coingecko.com/coins/images/71128/large/slx.png?1779455873"
    },
    {
      "rank": 2,
      "symbol": "SLX",
      "price": 403.0,
      "change_pct": 16.474,
      "vol_krw": 67778507503.4,
      "exchange": "업비트",
      "logo": "https://coin-images.coingecko.com/coins/images/71128/large/slx.png?1779455873"
    },
    {
      "rank": 3,
      "symbol": "XTER",
      "price": 20.7,
      "change_pct": 16.16,
      "vol_krw": 2032069747.77,
      "exchange": "빗썸",
      "logo": "https://coin-images.coingecko.com/coins/images/53378/large/xterio.jpg"
    },
    {
      "rank": 4,
      "symbol": "ID",
      "price": 58.6,
      "change_pct": 16.0396,
      "vol_krw": 56666621199.24,
      "exchange": "업비트",
      "logo": "https://coin-images.coingecko.com/coins/images/50882/large/hyperliquid.jpg"
    },
    {
      "rank": 5,
      "symbol": "ID",
      "price": 58.43,
      "change_pct": 14.17,
      "vol_krw": 5925879557.07,
      "exchange": "빗썸",
      "logo": "https://coin-images.coingecko.com/coins/images/50882/large/hyperliquid.jpg"
    },
    {
      "rank": 6,
      "symbol": "VERONA",
      "price": 241.0,
      "change_pct": 13.68,
      "vol_krw": 7716007232.49,
      "exchange": "빗썸",
      "logo": "https://coin-images.coingecko.com/coins/images/102174064/large/verona_logo.jpg"
    },
    {
      "rank": 7,
      "symbol": "SAHARA",
      "price": 19.53,
      "change_pct": 13.22,
      "vol_krw": 18686410430.09,
      "exchange": "빗썸",
      "logo": "https://coin-images.coingecko.com/coins/images/66681/large/Token_Logo_3x.png?1750362133"
    },
    {
      "rank": 8,
      "symbol": "STRAX",
      "price": 16.45,
      "change_pct": 12.44,
      "vol_krw": 1758337090.94,
      "exchange": "빗썸",
      "logo": "https://coin-images.coingecko.com/coins/images/531/large/Xertra_Logo_200x200.png"
    },
    {
      "rank": 9,
      "symbol": "STRAX",
      "price": 16.3,
      "change_pct": 9.396,
      "vol_krw": 6259948237.91,
      "exchange": "업비트",
      "logo": "https://coin-images.coingecko.com/coins/images/531/large/Xertra_Logo_200x200.png"
    },
    {
      "rank": 10,
      "symbol": "G",
      "price": 4.71,
      "change_pct": 8.52,
      "vol_krw": 2959419337.16,
      "exchange": "빗썸",
      "logo": "https://coin-images.coingecko.com/coins/images/68480/large/figure.png"
    }
  ],
  "per_exchange": {
    "upbit": {
      "volume_top10": [
        {
          "rank": 1,
          "symbol": "BTC",
          "price": 91300000,
          "change_pct": -3.376,
          "vol_krw": 172825409902.31,
          "exchange": "업비트",
          "logo": "https://coin-images.coingecko.com/coins/images/1/large/bitcoin.png?1696501400"
        },
        {
          "rank": 2,
          "symbol": "XRP",
          "price": 1610,
          "change_pct": -3.7657,
          "vol_krw": 138240973128.96,
          "exchange": "업비트",
          "logo": "https://coin-images.coingecko.com/coins/images/44/large/xrp-symbol-white-128.png?1696501442"
        },
        {
          "rank": 3,
          "symbol": "USDT",
          "price": 1527,
          "change_pct": 1.3271,
          "vol_krw": 80518148605.23,
          "exchange": "업비트",
          "logo": "https://coin-images.coingecko.com/coins/images/325/large/Tether.png?1696501661"
        },
        {
          "rank": 4,
          "symbol": "WLD",
          "price": 784.0,
          "change_pct": -4.3902,
          "vol_krw": 78915447198.43,
          "exchange": "업비트",
          "logo": "https://coin-images.coingecko.com/coins/images/31069/large/worldcoin.jpeg?1696529903"
        },
        {
          "rank": 5,
          "symbol": "ETH",
          "price": 2411000,
          "change_pct": -4.0971,
          "vol_krw": 73053344363.37,
          "exchange": "업비트",
          "logo": "https://coin-images.coingecko.com/coins/images/279/large/ethereum.png?1696501628"
        },
        {
          "rank": 6,
          "symbol": "SLX",
          "price": 403.0,
          "change_pct": 16.474,
          "vol_krw": 67778507503.4,
          "exchange": "업비트",
          "logo": "https://coin-images.coingecko.com/coins/images/71128/large/slx.png?1779455873"
        },
        {
          "rank": 7,
          "symbol": "ARX",
          "price": 397.0,
          "change_pct": -19.9597,
          "vol_krw": 67379308806.59,
          "exchange": "업비트",
          "logo": "https://coin-images.coingecko.com/coins/images/54948/large/Arcium_Logomark_04_400x400_circle.png?1782278429"
        },
        {
          "rank": 8,
          "symbol": "ID",
          "price": 58.6,
          "change_pct": 16.0396,
          "vol_krw": 56666621199.24,
          "exchange": "업비트",
          "logo": "https://coin-images.coingecko.com/coins/images/50882/large/hyperliquid.jpg"
        },
        {
          "rank": 9,
          "symbol": "SAHARA",
          "price": 19.7,
          "change_pct": 3.6842,
          "vol_krw": 48461997067.99,
          "exchange": "업비트",
          "logo": "https://coin-images.coingecko.com/coins/images/66681/large/Token_Logo_3x.png?1750362133"
        },
        {
          "rank": 10,
          "symbol": "XLM",
          "price": 280.0,
          "change_pct": -5.0847,
          "vol_krw": 29371609702.19,
          "exchange": "업비트",
          "logo": "https://coin-images.coingecko.com/coins/images/100/large/fmpFRHHQ_400x400.jpg?1735231350"
        }
      ],
      "gainers_top10": [
        {
          "rank": 1,
          "symbol": "SLX",
          "price": 403.0,
          "change_pct": 16.474,
          "vol_krw": 67778507503.4,
          "exchange": "업비트",
          "logo": "https://coin-images.coingecko.com/coins/images/71128/large/slx.png?1779455873"
        },
        {
          "rank": 2,
          "symbol": "ID",
          "price": 58.6,
          "change_pct": 16.0396,
          "vol_krw": 56666621199.24,
          "exchange": "업비트",
          "logo": "https://coin-images.coingecko.com/coins/images/50882/large/hyperliquid.jpg"
        },
        {
          "rank": 3,
          "symbol": "STRAX",
          "price": 16.3,
          "change_pct": 9.396,
          "vol_krw": 6259948237.91,
          "exchange": "업비트",
          "logo": "https://coin-images.coingecko.com/coins/images/531/large/Xertra_Logo_200x200.png"
        },
        {
          "rank": 4,
          "symbol": "G",
          "price": 4.77,
          "change_pct": 8.1633,
          "vol_krw": 16327211692.94,
          "exchange": "업비트",
          "logo": "https://coin-images.coingecko.com/coins/images/68480/large/figure.png"
        },
        {
          "rank": 5,
          "symbol": "CELO",
          "price": 98.5,
          "change_pct": 6.949,
          "vol_krw": 565462032.34,
          "exchange": "업비트",
          "logo": "https://coin-images.coingecko.com/coins/images/11090/large/InjXBNx9_400x400.jpg"
        },
        {
          "rank": 6,
          "symbol": "MASK",
          "price": 606.0,
          "change_pct": 4.6632,
          "vol_krw": 1480201608.71,
          "exchange": "업비트",
          "logo": "https://coin-images.coingecko.com/coins/images/14051/large/Mask_Network.jpg"
        },
        {
          "rank": 7,
          "symbol": "ONG",
          "price": 70.3,
          "change_pct": 4.3027,
          "vol_krw": 8694007557.4,
          "exchange": "업비트",
          "logo": "https://coin-images.coingecko.com/coins/images/5716/large/ONG_logo.png"
        },
        {
          "rank": 8,
          "symbol": "AAVE",
          "price": 113900,
          "change_pct": 4.2086,
          "vol_krw": 4278744938.38,
          "exchange": "업비트",
          "logo": "https://coin-images.coingecko.com/coins/images/12645/large/aave-token-round.png?1720472354"
        },
        {
          "rank": 9,
          "symbol": "SAHARA",
          "price": 19.7,
          "change_pct": 3.6842,
          "vol_krw": 48461997067.99,
          "exchange": "업비트",
          "logo": "https://coin-images.coingecko.com/coins/images/66681/large/Token_Logo_3x.png?1750362133"
        },
        {
          "rank": 10,
          "symbol": "MMT",
          "price": 280.0,
          "change_pct": 2.5641,
          "vol_krw": 6553536523.73,
          "exchange": "업비트",
          "logo": "https://coin-images.coingecko.com/coins/images/69899/large/4_icon_PFP_RGB.png"
        }
      ]
    },
    "bithumb": {
      "volume_top10": [
        {
          "rank": 1,
          "symbol": "USDT",
          "price": 1526,
          "change_pct": 1.06,
          "vol_krw": 82286692509.91,
          "exchange": "빗썸",
          "logo": "https://coin-images.coingecko.com/coins/images/325/large/Tether.png?1696501661"
        },
        {
          "rank": 2,
          "symbol": "WLD",
          "price": 785.0,
          "change_pct": -3.68,
          "vol_krw": 76541770577.92,
          "exchange": "빗썸",
          "logo": "https://coin-images.coingecko.com/coins/images/31069/large/worldcoin.jpeg?1696529903"
        },
        {
          "rank": 3,
          "symbol": "BTC",
          "price": 91316000,
          "change_pct": -3.0,
          "vol_krw": 54563765109.65,
          "exchange": "빗썸",
          "logo": "https://coin-images.coingecko.com/coins/images/1/large/bitcoin.png?1696501400"
        },
        {
          "rank": 4,
          "symbol": "XRP",
          "price": 1610,
          "change_pct": -3.13,
          "vol_krw": 47034353478.41,
          "exchange": "빗썸",
          "logo": "https://coin-images.coingecko.com/coins/images/44/large/xrp-symbol-white-128.png?1696501442"
        },
        {
          "rank": 5,
          "symbol": "ETH",
          "price": 2410000,
          "change_pct": -3.83,
          "vol_krw": 32225754145.98,
          "exchange": "빗썸",
          "logo": "https://coin-images.coingecko.com/coins/images/279/large/ethereum.png?1696501628"
        },
        {
          "rank": 6,
          "symbol": "SLX",
          "price": 398.0,
          "change_pct": 31.35,
          "vol_krw": 23568803866.03,
          "exchange": "빗썸",
          "logo": "https://coin-images.coingecko.com/coins/images/71128/large/slx.png?1779455873"
        },
        {
          "rank": 7,
          "symbol": "H",
          "price": 143.0,
          "change_pct": -6.54,
          "vol_krw": 19306418073.26,
          "exchange": "빗썸",
          "logo": "https://coin-images.coingecko.com/coins/images/66811/large/H_tokenLogo_original.png?1750581252"
        },
        {
          "rank": 8,
          "symbol": "SAHARA",
          "price": 19.53,
          "change_pct": 13.22,
          "vol_krw": 18686410430.09,
          "exchange": "빗썸",
          "logo": "https://coin-images.coingecko.com/coins/images/66681/large/Token_Logo_3x.png?1750362133"
        },
        {
          "rank": 9,
          "symbol": "XPLA",
          "price": 9.96,
          "change_pct": -2.22,
          "vol_krw": 13357064738.08,
          "exchange": "빗썸",
          "logo": null
        },
        {
          "rank": 10,
          "symbol": "SOL",
          "price": 100500,
          "change_pct": -3.37,
          "vol_krw": 11991207530.29,
          "exchange": "빗썸",
          "logo": "https://coin-images.coingecko.com/coins/images/4128/large/solana.png?1718769756"
        }
      ],
      "gainers_top10": [
        {
          "rank": 1,
          "symbol": "SLX",
          "price": 398.0,
          "change_pct": 31.35,
          "vol_krw": 23568803866.03,
          "exchange": "빗썸",
          "logo": "https://coin-images.coingecko.com/coins/images/71128/large/slx.png?1779455873"
        },
        {
          "rank": 2,
          "symbol": "XTER",
          "price": 20.7,
          "change_pct": 16.16,
          "vol_krw": 2032069747.77,
          "exchange": "빗썸",
          "logo": "https://coin-images.coingecko.com/coins/images/53378/large/xterio.jpg"
        },
        {
          "rank": 3,
          "symbol": "ID",
          "price": 58.43,
          "change_pct": 14.17,
          "vol_krw": 5925879557.07,
          "exchange": "빗썸",
          "logo": "https://coin-images.coingecko.com/coins/images/50882/large/hyperliquid.jpg"
        },
        {
          "rank": 4,
          "symbol": "VERONA",
          "price": 241.0,
          "change_pct": 13.68,
          "vol_krw": 7716007232.49,
          "exchange": "빗썸",
          "logo": "https://coin-images.coingecko.com/coins/images/102174064/large/verona_logo.jpg"
        },
        {
          "rank": 5,
          "symbol": "SAHARA",
          "price": 19.53,
          "change_pct": 13.22,
          "vol_krw": 18686410430.09,
          "exchange": "빗썸",
          "logo": "https://coin-images.coingecko.com/coins/images/66681/large/Token_Logo_3x.png?1750362133"
        },
        {
          "rank": 6,
          "symbol": "STRAX",
          "price": 16.45,
          "change_pct": 12.44,
          "vol_krw": 1758337090.94,
          "exchange": "빗썸",
          "logo": "https://coin-images.coingecko.com/coins/images/531/large/Xertra_Logo_200x200.png"
        },
        {
          "rank": 7,
          "symbol": "G",
          "price": 4.71,
          "change_pct": 8.52,
          "vol_krw": 2959419337.16,
          "exchange": "빗썸",
          "logo": "https://coin-images.coingecko.com/coins/images/68480/large/figure.png"
        },
        {
          "rank": 8,
          "symbol": "POLA",
          "price": 4.07,
          "change_pct": 8.43,
          "vol_krw": 580575024.95,
          "exchange": "빗썸",
          "logo": "https://coin-images.coingecko.com/coins/images/13817/large/tHQrxdYQ_400x400.png"
        },
        {
          "rank": 9,
          "symbol": "MANTA",
          "price": 124.0,
          "change_pct": 5.98,
          "vol_krw": 2231605464.61,
          "exchange": "빗썸",
          "logo": null
        },
        {
          "rank": 10,
          "symbol": "AAVE",
          "price": 114100,
          "change_pct": 5.36,
          "vol_krw": 881692888.83,
          "exchange": "빗썸",
          "logo": "https://coin-images.coingecko.com/coins/images/12645/large/aave-token-round.png?1720472354"
        }
      ]
    },
    "coinone": {
      "volume_top10": [
        {
          "rank": 1,
          "symbol": "USDT",
          "price": 1526,
          "change_pct": 1.0596,
          "vol_krw": 28734062359.65,
          "exchange": "코인원",
          "logo": "https://coin-images.coingecko.com/coins/images/325/large/Tether.png?1696501661"
        },
        {
          "rank": 2,
          "symbol": "RLUSD",
          "price": 1527,
          "change_pct": 0.9921,
          "vol_krw": 24828405389.34,
          "exchange": "코인원",
          "logo": "https://coin-images.coingecko.com/coins/images/39651/large/RLUSD_200x200_%281%29.png?1727376633"
        },
        {
          "rank": 3,
          "symbol": "USDC",
          "price": 1529,
          "change_pct": 1.2583,
          "vol_krw": 10185477783.96,
          "exchange": "코인원",
          "logo": "https://coin-images.coingecko.com/coins/images/6319/large/USDC.png?1769615602"
        },
        {
          "rank": 4,
          "symbol": "BTC",
          "price": 91280000,
          "change_pct": -3.038,
          "vol_krw": 7321834920.18,
          "exchange": "코인원",
          "logo": "https://coin-images.coingecko.com/coins/images/1/large/bitcoin.png?1696501400"
        },
        {
          "rank": 5,
          "symbol": "XRP",
          "price": 1610,
          "change_pct": -3.1288,
          "vol_krw": 5007042386.65,
          "exchange": "코인원",
          "logo": "https://coin-images.coingecko.com/coins/images/44/large/xrp-symbol-white-128.png?1696501442"
        },
        {
          "rank": 6,
          "symbol": "WLD",
          "price": 789.0,
          "change_pct": -3.3088,
          "vol_krw": 2730724443.92,
          "exchange": "코인원",
          "logo": "https://coin-images.coingecko.com/coins/images/31069/large/worldcoin.jpeg?1696529903"
        },
        {
          "rank": 7,
          "symbol": "ETH",
          "price": 2410000,
          "change_pct": -3.8692,
          "vol_krw": 2612435194.59,
          "exchange": "코인원",
          "logo": "https://coin-images.coingecko.com/coins/images/279/large/ethereum.png?1696501628"
        },
        {
          "rank": 8,
          "symbol": "DOGE",
          "price": 112.9,
          "change_pct": -4.5647,
          "vol_krw": 977985876.16,
          "exchange": "코인원",
          "logo": "https://coin-images.coingecko.com/coins/images/5/large/dogecoin.png?1696501409"
        },
        {
          "rank": 9,
          "symbol": "SOL",
          "price": 100400,
          "change_pct": -3.3686,
          "vol_krw": 848266550.67,
          "exchange": "코인원",
          "logo": "https://coin-images.coingecko.com/coins/images/4128/large/solana.png?1718769756"
        },
        {
          "rank": 10,
          "symbol": "XLM",
          "price": 280.4,
          "change_pct": -4.3982,
          "vol_krw": 549280229.98,
          "exchange": "코인원",
          "logo": "https://coin-images.coingecko.com/coins/images/100/large/fmpFRHHQ_400x400.jpg?1735231350"
        }
      ],
      "gainers_top10": [
        {
          "rank": 1,
          "symbol": "USDC",
          "price": 1529,
          "change_pct": 1.2583,
          "vol_krw": 10185477783.96,
          "exchange": "코인원",
          "logo": "https://coin-images.coingecko.com/coins/images/6319/large/USDC.png?1769615602"
        },
        {
          "rank": 2,
          "symbol": "USDT",
          "price": 1526,
          "change_pct": 1.0596,
          "vol_krw": 28734062359.65,
          "exchange": "코인원",
          "logo": "https://coin-images.coingecko.com/coins/images/325/large/Tether.png?1696501661"
        },
        {
          "rank": 3,
          "symbol": "RLUSD",
          "price": 1527,
          "change_pct": 0.9921,
          "vol_krw": 24828405389.34,
          "exchange": "코인원",
          "logo": "https://coin-images.coingecko.com/coins/images/39651/large/RLUSD_200x200_%281%29.png?1727376633"
        },
        {
          "rank": 4,
          "symbol": "TRX",
          "price": 497.3,
          "change_pct": 0.2419,
          "vol_krw": 246476177.39,
          "exchange": "코인원",
          "logo": "https://coin-images.coingecko.com/coins/images/1094/large/photo_2026-04-13_09-59-16.png?1776048311"
        },
        {
          "rank": 5,
          "symbol": "ONDO",
          "price": 457.7,
          "change_pct": -2.4094,
          "vol_krw": 199604810.4,
          "exchange": "코인원",
          "logo": "https://coin-images.coingecko.com/coins/images/26580/large/ONDO.png?1696525656"
        },
        {
          "rank": 6,
          "symbol": "SUI",
          "price": 1024,
          "change_pct": -2.6616,
          "vol_krw": 205071434.28,
          "exchange": "코인원",
          "logo": "https://coin-images.coingecko.com/coins/images/26375/large/sui-ocean-square.png?1727791290"
        },
        {
          "rank": 7,
          "symbol": "BTC",
          "price": 91280000,
          "change_pct": -3.038,
          "vol_krw": 7321834920.18,
          "exchange": "코인원",
          "logo": "https://coin-images.coingecko.com/coins/images/1/large/bitcoin.png?1696501400"
        },
        {
          "rank": 8,
          "symbol": "XRP",
          "price": 1610,
          "change_pct": -3.1288,
          "vol_krw": 5007042386.65,
          "exchange": "코인원",
          "logo": "https://coin-images.coingecko.com/coins/images/44/large/xrp-symbol-white-128.png?1696501442"
        },
        {
          "rank": 9,
          "symbol": "WLD",
          "price": 789.0,
          "change_pct": -3.3088,
          "vol_krw": 2730724443.92,
          "exchange": "코인원",
          "logo": "https://coin-images.coingecko.com/coins/images/31069/large/worldcoin.jpeg?1696529903"
        },
        {
          "rank": 10,
          "symbol": "SOL",
          "price": 100400,
          "change_pct": -3.3686,
          "vol_krw": 848266550.67,
          "exchange": "코인원",
          "logo": "https://coin-images.coingecko.com/coins/images/4128/large/solana.png?1718769756"
        }
      ]
    },
    "korbit": {
      "volume_top10": [
        {
          "rank": 1,
          "symbol": "USDT",
          "price": 1526,
          "change_pct": 1.13,
          "vol_krw": 10650404212.75,
          "exchange": "코빗",
          "logo": "https://coin-images.coingecko.com/coins/images/325/large/Tether.png?1696501661"
        },
        {
          "rank": 2,
          "symbol": "BTC",
          "price": 91309000,
          "change_pct": -3.03,
          "vol_krw": 2388114928.9,
          "exchange": "코빗",
          "logo": "https://coin-images.coingecko.com/coins/images/1/large/bitcoin.png?1696501400"
        },
        {
          "rank": 3,
          "symbol": "XRP",
          "price": 1610,
          "change_pct": -3.01,
          "vol_krw": 2001635727.04,
          "exchange": "코빗",
          "logo": "https://coin-images.coingecko.com/coins/images/44/large/xrp-symbol-white-128.png?1696501442"
        },
        {
          "rank": 4,
          "symbol": "SOL",
          "price": 100600,
          "change_pct": -3.18,
          "vol_krw": 1014459186.51,
          "exchange": "코빗",
          "logo": "https://coin-images.coingecko.com/coins/images/4128/large/solana.png?1718769756"
        },
        {
          "rank": 5,
          "symbol": "ETH",
          "price": 2400000,
          "change_pct": -4.19,
          "vol_krw": 906487225.82,
          "exchange": "코빗",
          "logo": "https://coin-images.coingecko.com/coins/images/279/large/ethereum.png?1696501628"
        },
        {
          "rank": 6,
          "symbol": "WLD",
          "price": 787.7,
          "change_pct": -3.52,
          "vol_krw": 618330351.5,
          "exchange": "코빗",
          "logo": "https://coin-images.coingecko.com/coins/images/31069/large/worldcoin.jpeg?1696529903"
        },
        {
          "rank": 7,
          "symbol": "DOGE",
          "price": 112.8,
          "change_pct": -4.81,
          "vol_krw": 525329291.95,
          "exchange": "코빗",
          "logo": "https://coin-images.coingecko.com/coins/images/5/large/dogecoin.png?1696501409"
        },
        {
          "rank": 8,
          "symbol": "USDC",
          "price": 1525,
          "change_pct": 0.99,
          "vol_krw": 183193315.69,
          "exchange": "코빗",
          "logo": "https://coin-images.coingecko.com/coins/images/6319/large/USDC.png?1769615602"
        },
        {
          "rank": 9,
          "symbol": "SUI",
          "price": 1027,
          "change_pct": -2.75,
          "vol_krw": 142343222.21,
          "exchange": "코빗",
          "logo": "https://coin-images.coingecko.com/coins/images/26375/large/sui-ocean-square.png?1727791290"
        },
        {
          "rank": 10,
          "symbol": "XLM",
          "price": 279.1,
          "change_pct": -4.65,
          "vol_krw": 77408634.03,
          "exchange": "코빗",
          "logo": "https://coin-images.coingecko.com/coins/images/100/large/fmpFRHHQ_400x400.jpg?1735231350"
        }
      ],
      "gainers_top10": [
        {
          "rank": 1,
          "symbol": "USDT",
          "price": 1526,
          "change_pct": 1.13,
          "vol_krw": 10650404212.75,
          "exchange": "코빗",
          "logo": "https://coin-images.coingecko.com/coins/images/325/large/Tether.png?1696501661"
        },
        {
          "rank": 2,
          "symbol": "USDC",
          "price": 1525,
          "change_pct": 0.99,
          "vol_krw": 183193315.69,
          "exchange": "코빗",
          "logo": "https://coin-images.coingecko.com/coins/images/6319/large/USDC.png?1769615602"
        },
        {
          "rank": 3,
          "symbol": "SUI",
          "price": 1027,
          "change_pct": -2.75,
          "vol_krw": 142343222.21,
          "exchange": "코빗",
          "logo": "https://coin-images.coingecko.com/coins/images/26375/large/sui-ocean-square.png?1727791290"
        },
        {
          "rank": 4,
          "symbol": "XRP",
          "price": 1610,
          "change_pct": -3.01,
          "vol_krw": 2001635727.04,
          "exchange": "코빗",
          "logo": "https://coin-images.coingecko.com/coins/images/44/large/xrp-symbol-white-128.png?1696501442"
        },
        {
          "rank": 5,
          "symbol": "BTC",
          "price": 91309000,
          "change_pct": -3.03,
          "vol_krw": 2388114928.9,
          "exchange": "코빗",
          "logo": "https://coin-images.coingecko.com/coins/images/1/large/bitcoin.png?1696501400"
        },
        {
          "rank": 6,
          "symbol": "SOL",
          "price": 100600,
          "change_pct": -3.18,
          "vol_krw": 1014459186.51,
          "exchange": "코빗",
          "logo": "https://coin-images.coingecko.com/coins/images/4128/large/solana.png?1718769756"
        },
        {
          "rank": 7,
          "symbol": "WLD",
          "price": 787.7,
          "change_pct": -3.52,
          "vol_krw": 618330351.5,
          "exchange": "코빗",
          "logo": "https://coin-images.coingecko.com/coins/images/31069/large/worldcoin.jpeg?1696529903"
        },
        {
          "rank": 8,
          "symbol": "ETH",
          "price": 2400000,
          "change_pct": -4.19,
          "vol_krw": 906487225.82,
          "exchange": "코빗",
          "logo": "https://coin-images.coingecko.com/coins/images/279/large/ethereum.png?1696501628"
        },
        {
          "rank": 9,
          "symbol": "DOGE",
          "price": 112.8,
          "change_pct": -4.81,
          "vol_krw": 525329291.95,
          "exchange": "코빗",
          "logo": "https://coin-images.coingecko.com/coins/images/5/large/dogecoin.png?1696501409"
        }
      ]
    },
    "gopax": {
      "volume_top10": [
        {
          "rank": 1,
          "symbol": "GHUB",
          "price": 5.23,
          "change_pct": -2.6071,
          "vol_krw": 376187577.69,
          "exchange": "고팍스",
          "logo": null
        },
        {
          "rank": 2,
          "symbol": "STOC",
          "price": 594.0,
          "change_pct": 1.1925,
          "vol_krw": 149288946.19,
          "exchange": "고팍스",
          "logo": null
        },
        {
          "rank": 3,
          "symbol": "EGGT",
          "price": 543.0,
          "change_pct": -0.9124,
          "vol_krw": 136619781.57,
          "exchange": "고팍스",
          "logo": null
        },
        {
          "rank": 4,
          "symbol": "USDT",
          "price": 1526,
          "change_pct": 1.0596,
          "vol_krw": 136496557.63,
          "exchange": "고팍스",
          "logo": "https://coin-images.coingecko.com/coins/images/325/large/Tether.png?1696501661"
        },
        {
          "rank": 5,
          "symbol": "LOCUS",
          "price": 9.88,
          "change_pct": -0.9027,
          "vol_krw": 63012867.84,
          "exchange": "고팍스",
          "logo": null
        },
        {
          "rank": 6,
          "symbol": "XRP",
          "price": 1615,
          "change_pct": -2.7694,
          "vol_krw": 61718461.34,
          "exchange": "고팍스",
          "logo": "https://coin-images.coingecko.com/coins/images/44/large/xrp-symbol-white-128.png?1696501442"
        },
        {
          "rank": 7,
          "symbol": "CRETA",
          "price": 3.02,
          "change_pct": 2.3729,
          "vol_krw": 46130579.05,
          "exchange": "고팍스",
          "logo": null
        },
        {
          "rank": 8,
          "symbol": "ETH",
          "price": 2400000,
          "change_pct": -5.6604,
          "vol_krw": 23653677.72,
          "exchange": "고팍스",
          "logo": "https://coin-images.coingecko.com/coins/images/279/large/ethereum.png?1696501628"
        },
        {
          "rank": 9,
          "symbol": "BTC",
          "price": 91000000,
          "change_pct": -4.2065,
          "vol_krw": 17772568.45,
          "exchange": "고팍스",
          "logo": "https://coin-images.coingecko.com/coins/images/1/large/bitcoin.png?1696501400"
        },
        {
          "rank": 10,
          "symbol": "CLE",
          "price": 9.48,
          "change_pct": 0.9585,
          "vol_krw": 14756265.9,
          "exchange": "고팍스",
          "logo": null
        }
      ],
      "gainers_top10": [
        {
          "rank": 1,
          "symbol": "STOC",
          "price": 594.0,
          "change_pct": 1.1925,
          "vol_krw": 149288946.19,
          "exchange": "고팍스",
          "logo": null
        },
        {
          "rank": 2,
          "symbol": "USDT",
          "price": 1526,
          "change_pct": 1.0596,
          "vol_krw": 136496557.63,
          "exchange": "고팍스",
          "logo": "https://coin-images.coingecko.com/coins/images/325/large/Tether.png?1696501661"
        },
        {
          "rank": 3,
          "symbol": "EGGT",
          "price": 543.0,
          "change_pct": -0.9124,
          "vol_krw": 136619781.57,
          "exchange": "고팍스",
          "logo": null
        },
        {
          "rank": 4,
          "symbol": "GHUB",
          "price": 5.23,
          "change_pct": -2.6071,
          "vol_krw": 376187577.69,
          "exchange": "고팍스",
          "logo": null
        }
      ]
    }
  }
}