{
  "schema_version": "1.0.0",
  "generated_at": "2026-06-10T11:49:36+09:00",
  "run_id": "1781059776",
  "status": "ok",
  "failures": [],
  "btc": {
    "name": "Bitcoin",
    "symbol": "btc",
    "image": "https://coin-images.coingecko.com/coins/images/1/large/bitcoin.png?1696501400",
    "price": 61255.0,
    "chg": -2.32867
  },
  "eth": {
    "name": "Ethereum",
    "symbol": "eth",
    "image": "https://coin-images.coingecko.com/coins/images/279/large/ethereum.png?1696501628",
    "price": 1622.44,
    "chg": -2.47222
  },
  "gainers": [
    {
      "name": "Bitway",
      "symbol": "btw",
      "image": "https://coin-images.coingecko.com/coins/images/71205/large/bitway.png?1766388722",
      "price": 0.100557,
      "chg": 68.1454
    },
    {
      "name": "Humanity",
      "symbol": "h",
      "image": "https://coin-images.coingecko.com/coins/images/66811/large/H_tokenLogo_original.png?1750581252",
      "price": 0.170074,
      "chg": 41.79251
    },
    {
      "name": "Velvet",
      "symbol": "velvet",
      "image": "https://coin-images.coingecko.com/coins/images/67194/large/velvet.jpg?1752054592",
      "price": 0.375919,
      "chg": 17.61215
    },
    {
      "name": "Unibase",
      "symbol": "ub",
      "image": "https://coin-images.coingecko.com/coins/images/69108/large/unibase.png?1757501820",
      "price": 0.137547,
      "chg": 16.63951
    },
    {
      "name": "Sentient",
      "symbol": "sent",
      "image": "https://coin-images.coingecko.com/coins/images/70508/large/SENTIENT-Icon-BlushForce-L.png?1762267532",
      "price": 0.01643635,
      "chg": 15.43666
    },
    {
      "name": "THORChain",
      "symbol": "rune",
      "image": "https://coin-images.coingecko.com/coins/images/6595/large/THORChain_Circle_Gradient__with_Lightning_Bolt_-_Square_Transparent_Background_200px.png?1768635632",
      "price": 0.394404,
      "chg": 14.86758
    },
    {
      "name": "HOME",
      "symbol": "home",
      "image": "https://coin-images.coingecko.com/coins/images/54873/large/defi-app.png?1742235743",
      "price": 0.03157485,
      "chg": 14.77354
    },
    {
      "name": "Audiera",
      "symbol": "beat",
      "image": "https://coin-images.coingecko.com/coins/images/70428/large/audiera.png?1761964064",
      "price": 4.83,
      "chg": 13.71636
    },
    {
      "name": "WhiteBIT Coin",
      "symbol": "wbt",
      "image": "https://coin-images.coingecko.com/coins/images/27045/large/wbt_token.png?1696526096",
      "price": 50.61,
      "chg": 13.4963
    },
    {
      "name": "Chiliz",
      "symbol": "chz",
      "image": "https://coin-images.coingecko.com/coins/images/8834/large/CHZ_Token_updated.png?1696508986",
      "price": 0.0281899,
      "chg": 11.01259
    }
  ],
  "losers": [
    {
      "name": "SkyAI",
      "symbol": "skyai",
      "image": "https://coin-images.coingecko.com/coins/images/55294/large/1.png?1745517593",
      "price": 0.171728,
      "chg": -27.14115
    },
    {
      "name": "Siren",
      "symbol": "siren",
      "image": "https://coin-images.coingecko.com/coins/images/54479/large/siren.png?1739960056",
      "price": 0.872605,
      "chg": -26.27173
    },
    {
      "name": "LAB",
      "symbol": "lab",
      "image": "https://coin-images.coingecko.com/coins/images/70014/large/lab.png?1760352822",
      "price": 9.03,
      "chg": -25.57823
    },
    {
      "name": "DeXe",
      "symbol": "dexe",
      "image": "https://coin-images.coingecko.com/coins/images/12713/large/DEXE_token_logo.png?1696512514",
      "price": 19.38,
      "chg": -11.40893
    },
    {
      "name": "Hyperliquid",
      "symbol": "hype",
      "image": "https://coin-images.coingecko.com/coins/images/50882/large/hyperliquid.jpg?1729431300",
      "price": 55.73,
      "chg": -9.85883
    },
    {
      "name": "Falcon Finance",
      "symbol": "ff",
      "image": "https://coin-images.coingecko.com/coins/images/69121/large/ff.png?1757573403",
      "price": 0.074625,
      "chg": -7.38551
    },
    {
      "name": "币安人生 (BinanceLife)",
      "symbol": "币安人生",
      "image": "https://coin-images.coingecko.com/coins/images/69848/large/%E5%B8%81%E5%AE%89%E4%BA%BA%E7%94%9F.png?1759839225",
      "price": 0.68196,
      "chg": -6.28942
    },
    {
      "name": "Dash",
      "symbol": "dash",
      "image": "https://coin-images.coingecko.com/coins/images/19/large/dash-logo.png?1696501423",
      "price": 34.95,
      "chg": -5.25948
    },
    {
      "name": "Stellar",
      "symbol": "xlm",
      "image": "https://coin-images.coingecko.com/coins/images/100/large/fmpFRHHQ_400x400.jpg?1735231350",
      "price": 0.187456,
      "chg": -5.04975
    },
    {
      "name": "Kaspa",
      "symbol": "kas",
      "image": "https://coin-images.coingecko.com/coins/images/25751/large/kaspa-icon-exchanges.png?1696524837",
      "price": 0.03008388,
      "chg": -4.91588
    }
  ],
  "markets": [
    {
      "rank": 1,
      "name": "Bitcoin",
      "symbol": "btc",
      "image": "https://coin-images.coingecko.com/coins/images/1/large/bitcoin.png?1696501400",
      "price": 61255.0,
      "chg24h": -2.328671764421798,
      "chg7d": -8.352070369604595,
      "mcap": 1227879923267.0,
      "fdv": 1227879923267.0,
      "athChg": -51.41559
    },
    {
      "rank": 2,
      "name": "Ethereum",
      "symbol": "eth",
      "image": "https://coin-images.coingecko.com/coins/images/279/large/ethereum.png?1696501628",
      "price": 1622.44,
      "chg24h": -2.472216486961807,
      "chg7d": -13.101203348679983,
      "mcap": 195902898011.0,
      "fdv": 195902898011.0,
      "athChg": -67.19718
    },
    {
      "rank": 3,
      "name": "Tether",
      "symbol": "usdt",
      "image": "https://coin-images.coingecko.com/coins/images/325/large/Tether.png?1696501661",
      "price": 0.999273,
      "chg24h": -0.024101650899138755,
      "chg7d": 0.0630182648487604,
      "mcap": 186821613575.0,
      "fdv": 192284809917.0,
      "athChg": -24.47676
    },
    {
      "rank": 4,
      "name": "BNB",
      "symbol": "bnb",
      "image": "https://coin-images.coingecko.com/coins/images/825/large/bnb-icon2_2x.png?1696501970",
      "price": 586.67,
      "chg24h": -1.7328081350697027,
      "chg7d": -10.31271242491635,
      "mcap": 79076268954.0,
      "fdv": 79076267975.0,
      "athChg": -57.17692
    },
    {
      "rank": 5,
      "name": "USDC",
      "symbol": "usdc",
      "image": "https://coin-images.coingecko.com/coins/images/6319/large/USDC.png?1769615602",
      "price": 0.999764,
      "chg24h": 0.014984280363914833,
      "chg7d": 0.003089885933152366,
      "mcap": 75061112424.0,
      "fdv": 75086775735.0,
      "athChg": -4.19922
    },
    {
      "rank": 6,
      "name": "XRP",
      "symbol": "xrp",
      "image": "https://coin-images.coingecko.com/coins/images/44/large/xrp-symbol-white-128.png?1696501442",
      "price": 1.12,
      "chg24h": -2.6982386173081343,
      "chg7d": -8.64812535437849,
      "mcap": 69324424421.0,
      "fdv": 111700436976.0,
      "athChg": -69.36802
    },
    {
      "rank": 7,
      "name": "Solana",
      "symbol": "sol",
      "image": "https://coin-images.coingecko.com/coins/images/4128/large/solana.png?1718769756",
      "price": 64.31,
      "chg24h": -2.0526461943326657,
      "chg7d": -13.936931103386662,
      "mcap": 37264016062.0,
      "fdv": 40393347998.0,
      "athChg": -78.07384
    },
    {
      "rank": 8,
      "name": "TRON",
      "symbol": "trx",
      "image": "https://coin-images.coingecko.com/coins/images/1094/large/photo_2026-04-13_09-59-16.png?1776048311",
      "price": 0.321055,
      "chg24h": -1.1672439681143836,
      "chg7d": -3.5927845642124305,
      "mcap": 30445830883.0,
      "fdv": 30446060296.0,
      "athChg": -25.55901
    },
    {
      "rank": 9,
      "name": "Figure Heloc",
      "symbol": "figr_heloc",
      "image": "https://coin-images.coingecko.com/coins/images/68480/large/figure.png?1755863954",
      "price": 1.033,
      "chg24h": 0.5395250384230891,
      "chg7d": -0.24638139403142076,
      "mcap": 19249759964.0,
      "fdv": 19249759964.0,
      "athChg": -1.57522
    },
    {
      "rank": 10,
      "name": "Dogecoin",
      "symbol": "doge",
      "image": "https://coin-images.coingecko.com/coins/images/5/large/dogecoin.png?1696501409",
      "price": 0.083821,
      "chg24h": -1.1617091066754728,
      "chg7d": -9.642173331345758,
      "mcap": 12964722697.0,
      "fdv": 14282383201.0,
      "athChg": -88.54239
    },
    {
      "rank": 11,
      "name": "Hyperliquid",
      "symbol": "hype",
      "image": "https://coin-images.coingecko.com/coins/images/50882/large/hyperliquid.jpg?1729431300",
      "price": 55.73,
      "chg24h": -9.858834839589283,
      "chg7d": -20.377958714438897,
      "mcap": 12409066309.0,
      "fdv": 53291514037.0,
      "athChg": -26.1677
    },
    {
      "rank": 12,
      "name": "USDS",
      "symbol": "usds",
      "image": "https://coin-images.coingecko.com/coins/images/39926/large/usds.webp?1726666683",
      "price": 0.999689,
      "chg24h": 0.006765115083512654,
      "chg7d": -0.01289998423875282,
      "mcap": 10577149826.0,
      "fdv": 10582768874.0,
      "athChg": -13.22939
    },
    {
      "rank": 13,
      "name": "LEO Token",
      "symbol": "leo",
      "image": "https://coin-images.coingecko.com/coins/images/8418/large/leo-token.png?1696508607",
      "price": 9.46,
      "chg24h": 0.6938789629551468,
      "chg7d": -5.922714727782501,
      "mcap": 8709257419.0,
      "fdv": 9322452103.0,
      "athChg": -10.33948
    },
    {
      "rank": 14,
      "name": "Rain",
      "symbol": "rain",
      "image": "https://coin-images.coingecko.com/coins/images/69134/large/Rain_logo_1_.png?1762952191",
      "price": 0.01256645,
      "chg24h": -3.594772081574532,
      "chg7d": -9.009615611101706,
      "mcap": 7825182571.0,
      "fdv": 14450766374.0,
      "athChg": -14.96867
    },
    {
      "rank": 15,
      "name": "Zcash",
      "symbol": "zec",
      "image": "https://coin-images.coingecko.com/coins/images/486/large/circle-zcash-color.png?1696501740",
      "price": 428.05,
      "chg24h": -4.243293933765755,
      "chg7d": -31.630238750727663,
      "mcap": 7174154549.0,
      "fdv": 7174488996.0,
      "athChg": -86.58965
    },
    {
      "rank": 16,
      "name": "Canton",
      "symbol": "cc",
      "image": "https://coin-images.coingecko.com/coins/images/70468/large/Canton-Ticker_%281%29.png?1762826299",
      "price": 0.165391,
      "chg24h": 1.574771273451393,
      "chg7d": 9.808275217225669,
      "mcap": 6406180323.0,
      "fdv": 6406180323.0,
      "athChg": -14.92669
    },
    {
      "rank": 17,
      "name": "Stellar",
      "symbol": "xlm",
      "image": "https://coin-images.coingecko.com/coins/images/100/large/fmpFRHHQ_400x400.jpg?1735231350",
      "price": 0.187456,
      "chg24h": -5.0497469860284125,
      "chg7d": -16.589110606758258,
      "mcap": 6325798752.0,
      "fdv": 9373028771.0,
      "athChg": -78.51384
    },
    {
      "rank": 18,
      "name": "Cardano",
      "symbol": "ada",
      "image": "https://coin-images.coingecko.com/coins/images/975/large/cardano.png?1696502090",
      "price": 0.162479,
      "chg24h": -2.5174807657967797,
      "chg7d": -23.76135282814296,
      "mcap": 6043660495.0,
      "fdv": 7317441548.0,
      "athChg": -94.73653
    },
    {
      "rank": 19,
      "name": "WhiteBIT Coin",
      "symbol": "wbt",
      "image": "https://coin-images.coingecko.com/coins/images/27045/large/wbt_token.png?1696526096",
      "price": 50.61,
      "chg24h": 13.496299618748584,
      "chg7d": 3.448416835305897,
      "mcap": 5980949148.0,
      "fdv": 14874804898.0,
      "athChg": -21.12723
    },
    {
      "rank": 20,
      "name": "Monero",
      "symbol": "xmr",
      "image": "https://coin-images.coingecko.com/coins/images/69/large/monero_logo.png?1696501460",
      "price": 307.39,
      "chg24h": -3.100912987285523,
      "chg7d": -8.100250309434378,
      "mcap": 5769672496.0,
      "fdv": 5769677293.0,
      "athChg": -61.46701
    },
    {
      "rank": 21,
      "name": "Chainlink",
      "symbol": "link",
      "image": "https://coin-images.coingecko.com/coins/images/877/large/Chainlink_Logo_500.png?1760023405",
      "price": 7.72,
      "chg24h": -1.2058800221828414,
      "chg7d": -7.877378733283318,
      "mcap": 5616373342.0,
      "fdv": 7724348192.0,
      "athChg": -85.3452
    },
    {
      "rank": 22,
      "name": "USD1",
      "symbol": "usd1",
      "image": "https://coin-images.coingecko.com/coins/images/54977/large/USD1_1000x1000_transparent.png?1749297002",
      "price": 0.999049,
      "chg24h": 0.03251719621711795,
      "chg7d": 0.08748148747416933,
      "mcap": 4529219003.0,
      "fdv": 4529219003.0,
      "athChg": -2.52106
    },
    {
      "rank": 23,
      "name": "Ethena USDe",
      "symbol": "usde",
      "image": "https://coin-images.coingecko.com/coins/images/33613/large/usde.png?1733810059",
      "price": 0.999034,
      "chg24h": -0.023302556952719364,
      "chg7d": 0.008127160004762244,
      "mcap": 4479158334.0,
      "fdv": 4479158334.0,
      "athChg": -3.38228
    },
    {
      "rank": 24,
      "name": "Toncoin",
      "symbol": "ton",
      "image": "https://coin-images.coingecko.com/coins/images/17980/large/photo_2024-09-10_17.09.00.jpeg?1725963446",
      "price": 1.67,
      "chg24h": -1.5094438735156508,
      "chg7d": -16.817713458981736,
      "mcap": 4463190560.0,
      "fdv": 8662217789.0,
      "athChg": -79.82413
    },
    {
      "rank": 25,
      "name": "Dai",
      "symbol": "dai",
      "image": "https://coin-images.coingecko.com/coins/images/9956/large/Badge_Dai.png?1696509996",
      "price": 0.999698,
      "chg24h": 0.005049318547190736,
      "chg7d": -0.000294538990792005,
      "mcap": 4202825162.0,
      "fdv": 4201855641.0,
      "athChg": -17.99325
    },
    {
      "rank": 26,
      "name": "Bitcoin Cash",
      "symbol": "bch",
      "image": "https://coin-images.coingecko.com/coins/images/780/large/bitcoin-cash-circle.png?1696501932",
      "price": 200.52,
      "chg24h": -2.127235428830125,
      "chg7d": -25.655523137097468,
      "mcap": 4019965338.0,
      "fdv": 4019975991.0,
      "athChg": -94.70328
    },
    {
      "rank": 27,
      "name": "MemeCore",
      "symbol": "m",
      "image": "https://coin-images.coingecko.com/coins/images/53247/large/square-bg-transparent.png?1752637478",
      "price": 2.93,
      "chg24h": -1.6971664160117905,
      "chg7d": -12.429878812530388,
      "mcap": 3834375147.0,
      "fdv": 15729770372.0,
      "athChg": -39.561
    },
    {
      "rank": 28,
      "name": "Hedera",
      "symbol": "hbar",
      "image": "https://coin-images.coingecko.com/coins/images/3688/large/hbar.png?1696504364",
      "price": 0.078436,
      "chg24h": -2.2612044747672,
      "chg7d": -9.89557174517338,
      "mcap": 3402625504.0,
      "fdv": 3922468949.0,
      "athChg": -86.19873
    },
    {
      "rank": 29,
      "name": "Litecoin",
      "symbol": "ltc",
      "image": "https://coin-images.coingecko.com/coins/images/2/large/litecoin.png?1696501400",
      "price": 42.5,
      "chg24h": 0.19795566307793658,
      "chg7d": -10.351647043123346,
      "mcap": 3284466676.0,
      "fdv": 3284541602.0,
      "athChg": -89.62496
    },
    {
      "rank": 30,
      "name": "Sui",
      "symbol": "sui",
      "image": "https://coin-images.coingecko.com/coins/images/26375/large/sui-ocean-square.png?1727791290",
      "price": 0.739708,
      "chg24h": -0.561384463652252,
      "chg7d": -9.200273329980872,
      "mcap": 2983869914.0,
      "fdv": 7405619590.0,
      "athChg": -86.16481
    },
    {
      "rank": 31,
      "name": "Circle USYC",
      "symbol": "usyc",
      "image": "https://coin-images.coingecko.com/coins/images/51054/large/Hashnote_SDYC_200x200.png?1730370965",
      "price": 1.13,
      "chg24h": null,
      "chg7d": 0.018923555372785283,
      "mcap": 2909819736.0,
      "fdv": 2909819736.0,
      "athChg": -0.0868
    },
    {
      "rank": 32,
      "name": "Avalanche",
      "symbol": "avax",
      "image": "https://coin-images.coingecko.com/coins/images/12559/large/Avalanche_Circle_RedWhite_Trans.png?1696512369",
      "price": 6.56,
      "chg24h": -0.9433198512036947,
      "chg7d": -20.160278755954273,
      "mcap": 2836004929.0,
      "fdv": 3044016870.0,
      "athChg": -95.46527
    },
    {
      "rank": 33,
      "name": "PayPal USD",
      "symbol": "pyusd",
      "image": "https://coin-images.coingecko.com/coins/images/31212/large/PYUSD_Token_Logo_2x.png?1765987788",
      "price": 0.999857,
      "chg24h": 0.008604662699388513,
      "chg7d": 0.009747147389628117,
      "mcap": 2831705072.0,
      "fdv": 2831705072.0,
      "athChg": -7.48607
    },
    {
      "rank": 34,
      "name": "LAB",
      "symbol": "lab",
      "image": "https://coin-images.coingecko.com/coins/images/70014/large/lab.png?1760352822",
      "price": 9.03,
      "chg24h": -25.578228062946774,
      "chg7d": -37.59535030706273,
      "mcap": 2824918814.0,
      "fdv": 9038500961.0,
      "athChg": -66.9274
    },
    {
      "rank": 35,
      "name": "NEAR Protocol",
      "symbol": "near",
      "image": "https://coin-images.coingecko.com/coins/images/10365/large/near.jpg?1696510367",
      "price": 2.14,
      "chg24h": 3.989825106182724,
      "chg7d": -20.870311436315955,
      "mcap": 2778623368.0,
      "fdv": 2778623362.0,
      "athChg": -89.50377
    },
    {
      "rank": 36,
      "name": "Shiba Inu",
      "symbol": "shib",
      "image": "https://coin-images.coingecko.com/coins/images/11939/large/shiba.png?1696511800",
      "price": 4.64e-06,
      "chg24h": -0.49969633338126485,
      "chg7d": -11.105014457259927,
      "mcap": 2733745698.0,
      "fdv": 2734936410.0,
      "athChg": -94.61654
    },
    {
      "rank": 37,
      "name": "Cronos",
      "symbol": "cro",
      "image": "https://coin-images.coingecko.com/coins/images/7310/large/cro_token_logo.png?1696507599",
      "price": 0.059568,
      "chg24h": -2.0920022295112246,
      "chg7d": -5.228217090196197,
      "mcap": 2670657846.0,
      "fdv": 5879373275.0,
      "athChg": -93.31098
    },
    {
      "rank": 38,
      "name": "Global Dollar",
      "symbol": "usdg",
      "image": "https://coin-images.coingecko.com/coins/images/51281/large/GDN_USDG_Token_200x200.png?1730484111",
      "price": 0.9999,
      "chg24h": -0.00809111895853869,
      "chg7d": 0.01567588986270709,
      "mcap": 2590119115.0,
      "fdv": 2590119115.0,
      "athChg": -39.56577
    },
    {
      "rank": 39,
      "name": "Tether Gold",
      "symbol": "xaut",
      "image": "https://coin-images.coingecko.com/coins/images/10481/large/logo.png?1774627372",
      "price": 4172.27,
      "chg24h": -3.3318817793276536,
      "chg7d": -6.235139798581782,
      "mcap": 2556849686.0,
      "fdv": 2952893371.0,
      "athChg": -24.24207
    },
    {
      "rank": 40,
      "name": "BlackRock USD Institutional Digital Liquidity Fund",
      "symbol": "buidl",
      "image": "https://coin-images.coingecko.com/coins/images/36291/large/blackrock.png?1711013223",
      "price": 1.0,
      "chg24h": 0.0,
      "chg7d": 0.0,
      "mcap": 2444639405.0,
      "fdv": 2444639405.0,
      "athChg": 0.0
    },
    {
      "rank": 41,
      "name": "Ondo US Dollar Yield",
      "symbol": "usdy",
      "image": "https://coin-images.coingecko.com/coins/images/31700/large/usdy_%281%29.png?1696530524",
      "price": 1.13,
      "chg24h": -0.3078065285584948,
      "chg7d": -0.6882937316518806,
      "mcap": 2139760118.0,
      "fdv": 2139760118.0,
      "athChg": -10.44322
    },
    {
      "rank": 42,
      "name": "Bittensor",
      "symbol": "tao",
      "image": "https://coin-images.coingecko.com/coins/images/28452/large/ARUsPeNQ_400x400.jpeg?1696527447",
      "price": 205.49,
      "chg24h": -2.817928744156626,
      "chg7d": -9.593564979013427,
      "mcap": 1976074770.0,
      "fdv": 4323793601.0,
      "athChg": -72.82585
    },
    {
      "rank": 43,
      "name": "PAX Gold",
      "symbol": "paxg",
      "image": "https://coin-images.coingecko.com/coins/images/9519/large/paxgold.png?1696509604",
      "price": 4181.98,
      "chg24h": -3.3803900044102893,
      "chg7d": -6.656164310253994,
      "mcap": 1910726490.0,
      "fdv": 1910726490.0,
      "athChg": -25.62688
    },
    {
      "rank": 44,
      "name": "Mantle",
      "symbol": "mnt",
      "image": "https://coin-images.coingecko.com/coins/images/30980/large/MNT_Token_Logo.png?1765516974",
      "price": 0.535221,
      "chg24h": -0.5905641307439791,
      "chg7d": -11.056903748413498,
      "mcap": 1768134280.0,
      "fdv": 3329983929.0,
      "athChg": -81.24446
    },
    {
      "rank": 45,
      "name": "World Liberty Financial",
      "symbol": "wlfi",
      "image": "https://coin-images.coingecko.com/coins/images/50767/large/wlfi.png?1756438915",
      "price": 0.05478,
      "chg24h": -1.6740629087445384,
      "chg7d": -8.086917788952213,
      "mcap": 1740730457.0,
      "fdv": 5478497352.0,
      "athChg": -83.46694
    },
    {
      "rank": 46,
      "name": "Ondo",
      "symbol": "ondo",
      "image": "https://coin-images.coingecko.com/coins/images/26580/large/ONDO.png?1696525656",
      "price": 0.3514,
      "chg24h": -1.1197949995780463,
      "chg7d": -9.838872506065428,
      "mcap": 1713488421.0,
      "fdv": 3518940375.0,
      "athChg": -83.58065
    },
    {
      "rank": 47,
      "name": "Worldcoin",
      "symbol": "wld",
      "image": "https://coin-images.coingecko.com/coins/images/31069/large/worldcoin.jpeg?1696529903",
      "price": 0.502072,
      "chg24h": 4.256359694556396,
      "chg7d": 26.66915321354032,
      "mcap": 1707335885.0,
      "fdv": 5034964473.0,
      "athChg": -95.7131
    },
    {
      "rank": 48,
      "name": "Ripple USD",
      "symbol": "rlusd",
      "image": "https://coin-images.coingecko.com/coins/images/39651/large/RLUSD_200x200_%281%29.png?1727376633",
      "price": 1.0,
      "chg24h": 0.01140932668124745,
      "chg7d": 0.020533716678355917,
      "mcap": 1651364819.0,
      "fdv": 1651364819.0,
      "athChg": -6.78654
    },
    {
      "rank": 49,
      "name": "Aster",
      "symbol": "aster",
      "image": "https://coin-images.coingecko.com/coins/images/69040/large/_ASTER.png?1757326782",
      "price": 0.615053,
      "chg24h": -0.6550362912507897,
      "chg7d": -9.04637334416621,
      "mcap": 1646768791.0,
      "fdv": 4811405874.0,
      "athChg": -74.46572
    },
    {
      "rank": 50,
      "name": "Polkadot",
      "symbol": "dot",
      "image": "https://coin-images.coingecko.com/coins/images/12171/large/polkadot.jpg?1766533446",
      "price": 0.946564,
      "chg24h": -0.7482981990429336,
      "chg7d": -12.59382210415247,
      "mcap": 1597816891.0,
      "fdv": 1597816891.0,
      "athChg": -98.27614
    },
    {
      "rank": 51,
      "name": "HTX DAO",
      "symbol": "htx",
      "image": "https://coin-images.coingecko.com/coins/images/35491/large/Frame_1321318576.png?1708908626",
      "price": 1.72e-06,
      "chg24h": -1.360047950893436,
      "chg7d": -2.4090724683635036,
      "mcap": 1555765563.0,
      "fdv": 1555765563.0,
      "athChg": -54.2158
    },
    {
      "rank": 52,
      "name": "Uniswap",
      "symbol": "uni",
      "image": "https://coin-images.coingecko.com/coins/images/12504/large/uniswap-logo.png?1720676669",
      "price": 2.45,
      "chg24h": -1.0844935369852613,
      "chg7d": -13.225429240310687,
      "mcap": 1524518607.0,
      "fdv": 2191067905.0,
      "athChg": -94.54232
    },
    {
      "rank": 53,
      "name": "OKB",
      "symbol": "okb",
      "image": "https://coin-images.coingecko.com/coins/images/4463/large/WeChat_Image_20220118095654.png?1696505053",
      "price": 70.4,
      "chg24h": -1.5458778159070021,
      "chg7d": -16.19232068423731,
      "mcap": 1478269181.0,
      "fdv": 1478269181.0,
      "athChg": -69.23975
    },
    {
      "rank": 54,
      "name": "Falcon USD",
      "symbol": "usdf",
      "image": "https://coin-images.coingecko.com/coins/images/54558/large/ff_200_X_200.png?1740741076",
      "price": 0.994654,
      "chg24h": -0.06677387000081277,
      "chg7d": 0.023876864137469013,
      "mcap": 1459008949.0,
      "fdv": 1459008949.0,
      "athChg": -7.43457
    },
    {
      "rank": 55,
      "name": "Audiera",
      "symbol": "beat",
      "image": "https://coin-images.coingecko.com/coins/images/70428/large/audiera.png?1761964064",
      "price": 4.83,
      "chg24h": 13.71636084836064,
      "chg7d": 334.37970433683927,
      "mcap": 1389805244.0,
      "fdv": 4825433415.0,
      "athChg": -2.13213
    },
    {
      "rank": 56,
      "name": "Pi Network",
      "symbol": "pi",
      "image": "https://coin-images.coingecko.com/coins/images/54342/large/pi_network.jpg?1739347576",
      "price": 0.126498,
      "chg24h": -0.9238403972549216,
      "chg7d": -9.113615403776103,
      "mcap": 1353166067.0,
      "fdv": 2081793949.0,
      "athChg": -95.76279
    },
    {
      "rank": 57,
      "name": "USDD",
      "symbol": "usdd",
      "image": "https://coin-images.coingecko.com/coins/images/25380/large/UUSD.jpg?1696524513",
      "price": 0.999083,
      "chg24h": -0.06435162375383648,
      "chg7d": -0.026243337614502302,
      "mcap": 1352014626.0,
      "fdv": 1352015599.0,
      "athChg": -4.97663
    },
    {
      "rank": 58,
      "name": "BFUSD",
      "symbol": "bfusd",
      "image": "https://coin-images.coingecko.com/coins/images/68227/large/bfusd.png?1755132827",
      "price": 0.998601,
      "chg24h": -0.020002316443181418,
      "chg7d": 0.02983286453848397,
      "mcap": 1318284612.0,
      "fdv": 1318284612.0,
      "athChg": -0.81674
    },
    {
      "rank": 59,
      "name": "Sky",
      "symbol": "sky",
      "image": "https://coin-images.coingecko.com/coins/images/39925/large/sky.jpg?1724827980",
      "price": 0.054912,
      "chg24h": -3.2844317281090314,
      "chg7d": -18.426242131372504,
      "mcap": 1277712229.0,
      "fdv": 1288115924.0,
      "athChg": -45.44987
    },
    {
      "rank": 60,
      "name": "Internet Computer",
      "symbol": "icp",
      "image": "https://coin-images.coingecko.com/coins/images/14495/large/Internet_Computer_logo.png?1696514180",
      "price": 2.26,
      "chg24h": -0.059945694317587776,
      "chg7d": -26.565582938014963,
      "mcap": 1254952835.0,
      "fdv": 1254952835.0,
      "athChg": -99.67639
    }
  ],
  "coins": [
    {
      "name": "Bitcoin",
      "symbol": "btc",
      "image": "https://coin-images.coingecko.com/coins/images/1/large/bitcoin.png?1696501400",
      "price": 61255.0,
      "chg": -2.32867
    },
    {
      "name": "Ethereum",
      "symbol": "eth",
      "image": "https://coin-images.coingecko.com/coins/images/279/large/ethereum.png?1696501628",
      "price": 1622.44,
      "chg": -2.47222
    },
    {
      "name": "BNB",
      "symbol": "bnb",
      "image": "https://coin-images.coingecko.com/coins/images/825/large/bnb-icon2_2x.png?1696501970",
      "price": 586.67,
      "chg": -1.73281
    },
    {
      "name": "XRP",
      "symbol": "xrp",
      "image": "https://coin-images.coingecko.com/coins/images/44/large/xrp-symbol-white-128.png?1696501442",
      "price": 1.12,
      "chg": -2.69824
    },
    {
      "name": "Solana",
      "symbol": "sol",
      "image": "https://coin-images.coingecko.com/coins/images/4128/large/solana.png?1718769756",
      "price": 64.31,
      "chg": -2.05265
    }
  ],
  "btc_dominance": 55.91860223278794,
  "eth_dominance": 8.918521773995371,
  "total_mcap": 2195079362006.4355,
  "total_vol": 89424695499.75038,
  "fear_greed": {
    "value": 9,
    "class": "Extreme Fear"
  },
  "kimchi": -1.5012793012431302,
  "domestic": {
    "btcKrw": 92010000.0,
    "ethKrw": 2436000.0,
    "usdKrw": 1523.7567,
    "btcVol": 119122783832.19804
  }
}